{
  "logNo": "224186307141",
  "title": "매출을 일으키는 상세페이지! 아직은 AI가 부족합니다. 이제 기획부터 시작하세요.",
  "addDate": "2026. 2. 23.",
  "categoryNo": "81",
  "url": "https://m.blog.naver.com/cookthedesign/224186307141",
  "content_html": "<div class=\"se-component se-image se-l-default\" id=\"SE-a257f24d-a800-4899-8473-d3fee7eaaee4\">\n<div class=\"se-component-content se-component-content-fit\">\n<div class=\"se-section se-section-image se-l-default se-section-align-\">\n<div class=\"se-module se-module-image\" style=\"\">\n<a class=\"se-module-image-link __se_image_link __se_link\" data-linkdata='{\"id\" : \"SE-a257f24d-a800-4899-8473-d3fee7eaaee4\", \"src\" : \"https://mblogthumb-phinf.pstatic.net/MjAyNjAyMTdfMTky/MDAxNzcxMzAxNzMxMDQ5.swnqMm5NnH2T29G28XcTH0yyCdareX5IFTXL8sNmI08g.6ER86p2GertmuJgkgxaMht5JE9VlVy4pX7L7HRqtywYg.PNG/Gemini_Generated_Image_7tm0v47tm0v47tm0.png\", \"originalWidth\" : \"2048\", \"originalHeight\" : \"2048\", \"linkUse\" : \"false\", \"link\" : \"\", \"fileSize\": \"8144727\" }' data-linktype=\"img\" href=\"#\" onclick=\"return false;\" style=\"\">\n<img alt=\"\" class=\"se-image-resource\" src=\"https://mblogthumb-phinf.pstatic.net/MjAyNjAyMTdfMTky/MDAxNzcxMzAxNzMxMDQ5.swnqMm5NnH2T29G28XcTH0yyCdareX5IFTXL8sNmI08g.6ER86p2GertmuJgkgxaMht5JE9VlVy4pX7L7HRqtywYg.PNG/Gemini_Generated_Image_7tm0v47tm0v47tm0.png?type=w966\"/>\n</a>\n</div>\n</div>\n</div>\n\n</div>\n<div class=\"se-component se-quotation se-l-quotation_underline\" id=\"SE-a82f1202-22fc-4693-b8bc-31f9e060e4d1\">\n<div class=\"se-component-content\">\n<div class=\"se-section se-section-quotation se-l-quotation_underline\">\n<blockquote class=\"se-quotation-container\">\n<div class=\"se-module se-module-text se-quote\"><!-- SE-TEXT { --><p class=\"se-text-paragraph se-text-paragraph-align-\" id=\"SE-197efc5a-5460-4896-9c73-2a77a2c259b8\" style=\"\"><span class=\"se-fs-fs19 se-ff-\" id=\"SE-66e0cf74-cd3d-42b8-98d1-c63c1f978cc8\" style=\"color:#555555;\"><b>상세페이지는 기획이 먼저다.</b></span></p><!-- } SE-TEXT --></div>\n</blockquote>\n</div>\n</div>\n</div>\n<div class=\"se-component se-text se-l-default\" id=\"SE-4c4727da-d853-4610-94a9-695887e02041\">\n<div class=\"se-component-content\">\n<div class=\"se-section se-section-text se-l-default\">\n<div class=\"se-module se-module-text\">\n<!-- SE-TEXT { --><p class=\"se-text-paragraph se-text-paragraph-align-\" id=\"SE-37dbda8c-39ed-45ea-aff0-eab9f74c2d43\" style=\"\"><span class=\"se-fs-fs16 se-ff-nanumsquare se-weight-unset\" id=\"SE-c8e67012-1dcf-4503-8587-f5293305ca10\" style=\"color:#555555;\">디자인은 그 다음이다.</span></p><!-- } SE-TEXT --><!-- SE-TEXT { --><p class=\"se-text-paragraph se-text-paragraph-align-\" id=\"SE-e2af6d89-d7b5-4415-9a24-ac54764d346f\" style=\"\"><span class=\"se-fs-fs16 se-ff-nanumsquare se-weight-unset\" id=\"SE-0b9f59a2-c015-4e78-b9d4-1163400b275e\" style=\"color:#555555;\">​</span></p><!-- } SE-TEXT --><!-- SE-TEXT { --><p class=\"se-text-paragraph se-text-paragraph-align-\" id=\"SE-5549b577-15b4-4177-9719-c87df5d16117\" style=\"\"><span class=\"se-fs-fs16 se-ff-nanumsquare se-weight-unset\" id=\"SE-c75c3d2b-5ed9-4431-9d2f-fba6e5718ab7\" style=\"color:#555555;\">​</span></p><!-- } SE-TEXT --><!-- SE-TEXT { --><p class=\"se-text-paragraph se-text-paragraph-align-\" id=\"SE-4092d581-4533-4f9e-b1da-32fee3da5547\" style=\"\"><span class=\"se-fs-fs16 se-ff-nanumsquare se-weight-unset\" id=\"SE-5c37d7b2-c16d-4b6b-bc20-e80ccbe9699e\" style=\"color:#555555;\">상세페이지를 만들 때 대부분은 이렇게 시작합니다.</span></p><!-- } SE-TEXT --><!-- SE-TEXT { --><p class=\"se-text-paragraph se-text-paragraph-align-\" id=\"SE-40bd6bad-e178-43fe-889e-53855dbd0330\" style=\"\"><span class=\"se-fs-fs16 se-ff-nanumsquare se-weight-unset\" id=\"SE-6d672522-d622-467d-ad8f-1f37e5e2a173\" style=\"color:#555555;\">​</span></p><!-- } SE-TEXT --><!-- SE-TEXT { --><p class=\"se-text-paragraph se-text-paragraph-align-\" id=\"SE-a0641c3d-88b2-44af-9d34-e7e7e1fa6f16\" style=\"\"><span class=\"se-fs-fs16 se-ff-nanumsquare se-weight-unset\" id=\"SE-76a8de30-0f18-492f-8ef8-bb9a51798baf\" style=\"color:#555555;\">“</span><span class=\"se-fs-fs16 se-ff-nanumsquare se-weight-unset\" id=\"SE-56f58561-1897-4f4f-b4b1-84cfb37d3efd\" style=\"color:#0078cb;\">디자인부터 예쁘게 해주세요.</span><span class=\"se-fs-fs16 se-ff-nanumsquare se-weight-unset\" id=\"SE-05a2bc5d-135e-41d3-acca-e90c87127bf7\" style=\"color:#555555;\">”</span></p><!-- } SE-TEXT --><!-- SE-TEXT { --><p class=\"se-text-paragraph se-text-paragraph-align-\" id=\"SE-420b7ebd-014c-4eef-b11f-c1861271380e\" style=\"\"><span class=\"se-fs-fs16 se-ff-nanumsquare se-weight-unset\" id=\"SE-d43bcde4-5c30-468f-a4d1-3fdd26ae8e4c\" style=\"color:#555555;\">​</span></p><!-- } SE-TEXT --><!-- SE-TEXT { --><p class=\"se-text-paragraph se-text-paragraph-align-\" id=\"SE-60e48e1a-560c-427c-a1f3-db83b6873f26\" style=\"\"><span class=\"se-fs-fs16 se-ff-nanumsquare se-weight-unset\" id=\"SE-3a92906a-dd8f-43f6-a004-57426746c660\" style=\"color:#555555;\">하지만 실제 매출을 만드는 건 디자인이 아니라 \"</span><span class=\"se-fs-fs19 se-ff-nanumsquare\" id=\"SE-48ee19b6-4413-4081-8fea-0146e1cfc4a5\" style=\"color:#aa1f91;\"><b>기획</b></span><span class=\"se-fs-fs16 se-ff-nanumsquare se-weight-unset\" id=\"SE-5acb2489-3eb3-4c6d-95c1-32a190883f25\" style=\"color:#555555;\">\"입니다.</span></p><!-- } SE-TEXT --><!-- SE-TEXT { --><p class=\"se-text-paragraph se-text-paragraph-align-\" id=\"SE-92854dc0-af65-484e-91cb-b1c8ce2ac93e\" style=\"\"><span class=\"se-fs-fs16 se-ff-nanumsquare se-weight-unset\" id=\"SE-f25c0efe-ee5f-428f-af61-cc0477656f09\" style=\"color:#555555;\">​</span></p><!-- } SE-TEXT --><!-- SE-TEXT { --><p class=\"se-text-paragraph se-text-paragraph-align-\" id=\"SE-86bcf818-8d15-4730-92a4-c405f9735dd6\" style=\"\"><span class=\"se-fs-fs16 se-ff-nanumsquare se-weight-unset\" id=\"SE-98711918-9d7a-4f49-a41c-18f6560a787a\" style=\"color:#555555;\">디자인은 보이게 만들고, 기획은 제품을 구매하게 만듭니다. 반드시 사도록 만들 수 있는 기획부터 점검하세요.</span></p><!-- } SE-TEXT -->\n</div>\n</div>\n</div>\n\n</div> <div class=\"se-component se-image se-l-default\" id=\"SE-ad2a1afa-ae19-416a-8721-15a59fc0c93e\">\n<div class=\"se-component-content se-component-content-normal\">\n<div class=\"se-section se-section-image se-l-default se-section-align-\" style=\"max-width:595px;\">\n<div class=\"se-module se-module-image\" style=\"\">\n<a class=\"se-module-image-link __se_image_link __se_link\" data-linkdata='{\"id\" : \"SE-ad2a1afa-ae19-416a-8721-15a59fc0c93e\", \"src\" : \"https://mblogthumb-phinf.pstatic.net/MjAyNjAyMTdfNjkg/MDAxNzcxMzA0MjM4NzI0.bL3FYOHwKvxm0LPCsMX9YK64qIsKobPsKkXxGtlTP8Qg.Aeo9oddXqqX52Cr3A-Y5PD8TF-WmsGm11W8WWqBYRGYg.PNG/%EC%83%B4%ED%91%B8_010.png\", \"originalWidth\" : \"595\", \"originalHeight\" : \"595\", \"linkUse\" : \"false\", \"link\" : \"\", \"fileSize\": \"545662\" }' data-linktype=\"img\" href=\"#\" onclick=\"return false;\" style=\"\">\n<img alt=\"\" class=\"se-image-resource\" src=\"https://mblogthumb-phinf.pstatic.net/MjAyNjAyMTdfNjkg/MDAxNzcxMzA0MjM4NzI0.bL3FYOHwKvxm0LPCsMX9YK64qIsKobPsKkXxGtlTP8Qg.Aeo9oddXqqX52Cr3A-Y5PD8TF-WmsGm11W8WWqBYRGYg.PNG/%EC%83%B4%ED%91%B8_010.png?type=w966\"/>\n</a>\n</div>\n</div>\n</div>\n\n</div>\n<div class=\"se-component se-horizontalLine se-l-default\" id=\"SE-27db514b-880a-4f61-a781-d4070fd3a9b1\">\n<div class=\"se-component-content\">\n<div class=\"se-section se-section-horizontalLine se-l-default se-section-align-\">\n<div class=\"se-module se-module-horizontalLine\">\n<hr class=\"se-hr\"/>\n</div>\n</div>\n</div>\n</div> <div class=\"se-component se-text se-l-default\" id=\"SE-decd31b5-d3d6-4e86-857f-2cfe3092ccf8\">\n<div class=\"se-component-content\">\n<div class=\"se-section se-section-text se-l-default\">\n<div class=\"se-module se-module-text\">\n<!-- SE-TEXT { --><p class=\"se-text-paragraph se-text-paragraph-align-\" id=\"SE-8a3ae997-0bdd-47b0-bf12-db8efe9c1a6b\" style=\"\"><span class=\"se-fs-fs19 se-ff-nanumsquare se-weight-unset\" id=\"SE-7095be34-0561-41ac-9b74-17195481a9a7\" style=\"color:#0078cb;\">■ 상세페이지 기획이란 무엇인가?</span></p><!-- } SE-TEXT --><!-- SE-TEXT { --><p class=\"se-text-paragraph se-text-paragraph-align-\" id=\"SE-8ad05124-e8f6-4eeb-bbe3-f774c5dd184f\" style=\"\"><span class=\"se-fs-fs16 se-ff-nanumsquare se-weight-unset\" id=\"SE-7821d957-1a64-4aa1-b091-c265f0eb96eb\" style=\"color:#555555;\">​</span></p><!-- } SE-TEXT --><!-- SE-TEXT { --><p class=\"se-text-paragraph se-text-paragraph-align-\" id=\"SE-b7942f80-cac6-4af7-b61f-b8e04ad55353\" style=\"\"><span class=\"se-fs-fs16 se-ff-nanumsquare se-weight-unset\" id=\"SE-7ed8d6c3-8aab-4cf1-aebe-a78b68596170\" style=\"color:#555555;\">상세페이지 기획은 문구를 짜는 일이 아닙니다.</span></p><!-- } SE-TEXT --><!-- SE-TEXT { --><p class=\"se-text-paragraph se-text-paragraph-align-\" id=\"SE-3d9a4f86-f99d-4fd7-adb0-8e6cec5b54e0\" style=\"\"><span class=\"se-fs-fs16 se-ff-nanumsquare se-weight-unset\" id=\"SE-7caeaf17-4653-41bf-a5fc-ca5ea8a86fe3\" style=\"color:#555555;\">​</span></p><!-- } SE-TEXT --><!-- SE-TEXT { --><p class=\"se-text-paragraph se-text-paragraph-align-\" id=\"SE-b097c7d0-836f-4e6c-8c26-45c85414a330\" style=\"\"><span class=\"se-fs-fs16 se-ff-nanumsquare se-weight-unset\" id=\"SE-17254c29-3d8f-4eb9-a805-26cf75c5feaa\" style=\"color:#555555;\">고객이 구매 버튼을 누르기까지의 </span><span class=\"se-fs-fs16 se-ff-nanumsquare\" id=\"SE-40766f31-4763-4d36-8daf-1dc0335e236f\" style=\"color:#555555;\"><b>흐름</b></span><span class=\"se-fs-fs16 se-ff-nanumsquare se-weight-unset\" id=\"SE-f4a71477-9087-4d88-8847-474efea3ac0d\" style=\"color:#555555;\">을</span><span class=\"se-fs-fs16 se-ff-nanumsquare\" id=\"SE-8e67c354-aca6-430b-b95e-6f48dc0b3803\" style=\"color:#555555;\"><b> 설계하는 일</b></span><span class=\"se-fs-fs16 se-ff-nanumsquare se-weight-unset\" id=\"SE-495c3506-aaf4-4a64-8249-19bb31efcd34\" style=\"color:#555555;\">입니다.</span></p><!-- } SE-TEXT --><!-- SE-TEXT { --><p class=\"se-text-paragraph se-text-paragraph-align-\" id=\"SE-b38364ae-ea52-454a-89b9-ea31c1f68c58\" style=\"\"><span class=\"se-fs-fs16 se-ff-nanumsquare se-weight-unset\" id=\"SE-42f46f40-172a-43f5-8150-0b31349f7558\" style=\"color:#555555;\">​</span></p><!-- } SE-TEXT --><!-- SE-TEXT { --><p class=\"se-text-paragraph se-text-paragraph-align-\" id=\"SE-30cbb6e5-aaca-4b05-8210-122d6ad8c75d\" style=\"\"><span class=\"se-fs-fs16 se-ff-nanumsquare se-weight-unset\" id=\"SE-c91ef204-64f9-4a65-83d5-3ec41ce02d4f\" style=\"color:#ff0010;\">□ 왜 이 제품을 봐야 하는지</span></p><!-- } SE-TEXT --><!-- SE-TEXT { --><p class=\"se-text-paragraph se-text-paragraph-align-\" id=\"SE-c42da3f8-b490-4294-8b9a-cfa408883f96\" style=\"\"><span class=\"se-fs-fs16 se-ff-nanumsquare se-weight-unset\" id=\"SE-16efd784-c078-4215-b004-edaed5d11cbd\" style=\"color:#ff0010;\">□ 왜 지금 사야 하는지</span></p><!-- } SE-TEXT --><!-- SE-TEXT { --><p class=\"se-text-paragraph se-text-paragraph-align-\" id=\"SE-0dba8f42-4927-4b68-be49-a3cf3a62d720\" style=\"\"><span class=\"se-fs-fs16 se-ff-nanumsquare se-weight-unset\" id=\"SE-cc825058-1d1c-4042-ae64-faa081f5a2c8\" style=\"color:#ff0010;\">□ 왜 다른 제품이 아닌지</span></p><!-- } SE-TEXT --><!-- SE-TEXT { --><p class=\"se-text-paragraph se-text-paragraph-align-\" id=\"SE-e761ec41-b6a3-4977-bd1c-bcf667124c3c\" style=\"\"><span class=\"se-fs-fs16 se-ff-nanumsquare se-weight-unset\" id=\"SE-02610a7d-a651-4474-9b2f-20b055518c12\" style=\"color:#555555;\">​</span></p><!-- } SE-TEXT --><!-- SE-TEXT { --><p class=\"se-text-paragraph se-text-paragraph-align-\" id=\"SE-536f9170-21b6-4d55-92c5-0df226a81d5e\" style=\"\"><span class=\"se-fs-fs16 se-ff-nanumsquare se-weight-unset\" id=\"SE-a484d036-2ab3-4b9b-b86f-42c79c08a2ad\" style=\"color:#555555;\">이 질문에 순서대로 답을 주는 것이 상세페이지 기획입니다.</span></p><!-- } SE-TEXT -->\n</div>\n</div>\n</div>\n\n</div> <div class=\"se-component se-image se-l-default\" id=\"SE-cfb5e715-36b2-4b38-ae6a-320f18034731\">\n<div class=\"se-component-content se-component-content-normal\">\n<div class=\"se-section se-section-image se-l-default se-section-align-\" style=\"max-width:653px;\">\n<div class=\"se-module se-module-image\" style=\"\">\n<a class=\"se-module-image-link __se_image_link __se_link\" data-linkdata='{\"id\" : \"SE-cfb5e715-36b2-4b38-ae6a-320f18034731\", \"src\" : \"https://mblogthumb-phinf.pstatic.net/MjAyNjAyMThfMjM4/MDAxNzcxMzk2MjQ2NjAw.0YpHtbqmtRD70c2tj2aFchooj8C_dtj3WYpfyqkonKcg._nllVRUfcyu4C9OykM4LRbqI2BSDyaaEIAH6JrofWHcg.PNG/%EC%83%B4%ED%91%B8_014.png\", \"originalWidth\" : \"653\", \"originalHeight\" : \"983\", \"linkUse\" : \"false\", \"link\" : \"\", \"fileSize\": \"434366\" }' data-linktype=\"img\" href=\"#\" onclick=\"return false;\" style=\"\">\n<img alt=\"\" class=\"se-image-resource\" src=\"https://mblogthumb-phinf.pstatic.net/MjAyNjAyMThfMjM4/MDAxNzcxMzk2MjQ2NjAw.0YpHtbqmtRD70c2tj2aFchooj8C_dtj3WYpfyqkonKcg._nllVRUfcyu4C9OykM4LRbqI2BSDyaaEIAH6JrofWHcg.PNG/%EC%83%B4%ED%91%B8_014.png?type=w966\"/>\n</a>\n</div>\n</div>\n</div>\n\n</div>\n<div class=\"se-component se-horizontalLine se-l-default\" id=\"SE-2511cdce-e170-4f2e-aeb4-b28204f92bf3\">\n<div class=\"se-component-content\">\n<div class=\"se-section se-section-horizontalLine se-l-default se-section-align-\">\n<div class=\"se-module se-module-horizontalLine\">\n<hr class=\"se-hr\"/>\n</div>\n</div>\n</div>\n</div> <div class=\"se-component se-text se-l-default\" id=\"SE-29a92a09-1ee0-4506-bf61-2744fa4c15eb\">\n<div class=\"se-component-content\">\n<div class=\"se-section se-section-text se-l-default\">\n<div class=\"se-module se-module-text\">\n<!-- SE-TEXT { --><p class=\"se-text-paragraph se-text-paragraph-align-\" id=\"SE-bde7580b-4251-4788-829b-2f17fa7f19a7\" style=\"\"><span class=\"se-fs-fs19 se-ff-nanumsquare se-weight-unset\" id=\"SE-cabd010c-5eda-4e4e-8185-c29cb1f4a106\" style=\"color:#0078cb;\">■ 상세페이지 기획의 출발점은 ‘제품’이 아니다.</span></p><!-- } SE-TEXT --><!-- SE-TEXT { --><p class=\"se-text-paragraph se-text-paragraph-align-\" id=\"SE-3f5a5dd7-8fcf-48d8-a6ac-dd2f2cd9b4b2\" style=\"\"><span class=\"se-fs-fs16 se-ff-nanumsquare se-weight-unset\" id=\"SE-947e0be3-9268-459c-a04d-ebf6e202d93a\" style=\"color:#555555;\">​</span></p><!-- } SE-TEXT --><!-- SE-TEXT { --><p class=\"se-text-paragraph se-text-paragraph-align-\" id=\"SE-18fb1a0e-af78-437e-819d-6e24c53fd26e\" style=\"\"><span class=\"se-fs-fs16 se-ff-nanumsquare se-weight-unset\" id=\"SE-ecedeaa4-1824-4b28-8620-67f9559e85f9\" style=\"color:#555555;\">상세페이지 기획에서 가장 큰 착각은 제품부터 생각하는 것입니다.</span></p><!-- } SE-TEXT --><!-- SE-TEXT { --><p class=\"se-text-paragraph se-text-paragraph-align-\" id=\"SE-ee7f559c-60d9-4e8b-8fd7-66d1098eccc9\" style=\"\"><span class=\"se-fs-fs16 se-ff-nanumsquare se-weight-unset\" id=\"SE-8cc7787c-23be-4d2a-bbe8-1567f884498d\" style=\"color:#555555;\">​</span></p><!-- } SE-TEXT --><!-- SE-TEXT { --><p class=\"se-text-paragraph se-text-paragraph-align-\" id=\"SE-afc53627-57e7-44c2-a33e-9455c2b7e2ac\" style=\"\"><span class=\"se-fs-fs16 se-ff-nanumsquare se-weight-unset\" id=\"SE-f1daf575-fbaf-4c3c-9753-75cdd9139e03\" style=\"color:#555555;\">“이 제품의 장점은 뭐지?”</span></p><!-- } SE-TEXT --><!-- SE-TEXT { --><p class=\"se-text-paragraph se-text-paragraph-align-\" id=\"SE-e2ea8d93-5ef9-4c42-b371-cc8f87dc2b23\" style=\"\"><span class=\"se-fs-fs16 se-ff-nanumsquare se-weight-unset\" id=\"SE-16d18d82-1df3-44ae-b41c-88dbbe8ec8ce\" style=\"color:#555555;\">​</span></p><!-- } SE-TEXT --><!-- SE-TEXT { --><p class=\"se-text-paragraph se-text-paragraph-align-\" id=\"SE-bf80b49e-ebf0-4bee-ad9b-bd5c4361ad3d\" style=\"\"><span class=\"se-fs-fs16 se-ff-nanumsquare se-weight-unset\" id=\"SE-08657918-c7b9-488f-ba7c-4c0b498786a9\" style=\"color:#555555;\">이 질문은 늦습니다.</span></p><!-- } SE-TEXT --><!-- SE-TEXT { --><p class=\"se-text-paragraph se-text-paragraph-align-\" id=\"SE-70352b7b-445e-499a-a3bf-318367fa9f18\" style=\"\"><span class=\"se-fs-fs16 se-ff-nanumsquare se-weight-unset\" id=\"SE-6ffb927d-e05f-4601-b7ae-cecae2c5041e\" style=\"color:#555555;\">먼저 나와야 할 질문은 이겁니다.</span></p><!-- } SE-TEXT --><!-- SE-TEXT { --><p class=\"se-text-paragraph se-text-paragraph-align-\" id=\"SE-3d6fc89e-93f4-4da3-aa43-ed4f91ac4650\" style=\"\"><span class=\"se-fs-fs16 se-ff-nanumsquare se-weight-unset\" id=\"SE-d973d70e-3d4d-4bda-97c1-4fbe0d36084f\" style=\"color:#555555;\">​</span></p><!-- } SE-TEXT --><!-- SE-TEXT { --><p class=\"se-text-paragraph se-text-paragraph-align-\" id=\"SE-00f17f88-c821-4660-9511-867c8ffe1c58\" style=\"\"><span class=\"se-fs-fs16 se-ff-nanumsquare\" id=\"SE-18c4f8e9-02e7-4d8e-81a4-af3c7460cb86\" style=\"color:#555555;\"><b>“이 제품을 찾는 사람은 어떤 불편함을 겪고 있을까?”</b></span></p><!-- } SE-TEXT --><!-- SE-TEXT { --><p class=\"se-text-paragraph se-text-paragraph-align-\" id=\"SE-cfa7d622-9b1d-4cb2-8a11-3b6bba7fca1c\" style=\"\"><span class=\"se-fs-fs16 se-ff-nanumsquare se-weight-unset\" id=\"SE-9a0681fc-2912-4fc9-9227-9b4b5474f807\" style=\"color:#555555;\">​</span></p><!-- } SE-TEXT --><!-- SE-TEXT { --><p class=\"se-text-paragraph se-text-paragraph-align-\" id=\"SE-dee6c507-8a28-4e62-81eb-efd0a2b351ca\" style=\"\"><span class=\"se-fs-fs16 se-ff-nanumsquare se-weight-unset\" id=\"SE-0fcfabe9-5750-4b52-b762-6ff100191e92\" style=\"color:#555555;\">고객은 문제를 해결하고 싶어서, 불편함을 없애고 싶어서, 지금보다 나아지고 싶어서, 상세페이지에 들어옵니다.</span></p><!-- } SE-TEXT --><!-- SE-TEXT { --><p class=\"se-text-paragraph se-text-paragraph-align-\" id=\"SE-2c54815b-b5b0-4537-9c3d-e40a87ff690d\" style=\"\"><span class=\"se-fs-fs16 se-ff-nanumsquare se-weight-unset\" id=\"SE-a724fabc-951d-458f-ab0e-cb179bf45f2b\" style=\"color:#555555;\">​</span></p><!-- } SE-TEXT --><!-- SE-TEXT { --><p class=\"se-text-paragraph se-text-paragraph-align-\" id=\"SE-ae5636ad-9eef-4795-b6f4-1fbfca3d7183\" style=\"\"><span class=\"se-fs-fs16 se-ff-nanumsquare se-weight-unset\" id=\"SE-2ca18d60-3964-4aa8-be24-52f10c6e46aa\" style=\"color:#555555;\">기획은 항상 고객의 문제에서 시작해야 합니다.</span></p><!-- } SE-TEXT -->\n</div>\n</div>\n</div>\n\n</div> <div class=\"se-component se-horizontalLine se-l-default\" id=\"SE-106694c9-d85c-4832-af96-1714369b59b1\">\n<div class=\"se-component-content\">\n<div class=\"se-section se-section-horizontalLine se-l-default se-section-align-\">\n<div class=\"se-module se-module-horizontalLine\">\n<hr class=\"se-hr\"/>\n</div>\n</div>\n</div>\n</div> <div class=\"se-component se-text se-l-default\" id=\"SE-43200328-e3ef-4529-987c-abdf23006897\">\n<div class=\"se-component-content\">\n<div class=\"se-section se-section-text se-l-default\">\n<div class=\"se-module se-module-text\">\n<!-- SE-TEXT { --><p class=\"se-text-paragraph se-text-paragraph-align-\" id=\"SE-e9c65cc3-9cc5-4451-bab6-3a73a6a862d0\" style=\"\"><span class=\"se-fs-fs19 se-ff-nanumsquare se-weight-unset\" id=\"SE-4545b3c0-5566-4247-87b1-4b197915a4d0\" style=\"color:#0078cb;\">■ 기능이 아닌 ‘변화’를 기획하라.</span></p><!-- } SE-TEXT --><!-- SE-TEXT { --><p class=\"se-text-paragraph se-text-paragraph-align-\" id=\"SE-cbbeb4ab-5765-45e2-94ae-4abb9c4b7173\" style=\"\"><span class=\"se-fs-fs16 se-ff-nanumsquare se-weight-unset\" id=\"SE-e48d2774-31b3-451e-9731-d25f4fa69549\" style=\"color:#555555;\">​</span></p><!-- } SE-TEXT --><!-- SE-TEXT { --><p class=\"se-text-paragraph se-text-paragraph-align-\" id=\"SE-85b8c1b3-3e6d-4ad1-bee4-77f38d0c4f3e\" style=\"\"><span class=\"se-fs-fs16 se-ff-nanumsquare se-weight-unset\" id=\"SE-c4c62ccc-3f1b-43b4-850f-00c45a9d0402\" style=\"color:#555555;\">상세페이지에 가장 많이 들어가는 요소는 성분, 스펙, 기능입니다.</span></p><!-- } SE-TEXT --><!-- SE-TEXT { --><p class=\"se-text-paragraph se-text-paragraph-align-\" id=\"SE-93a19954-0a31-444a-af85-10c15d7b38f7\" style=\"\"><span class=\"se-fs-fs16 se-ff-nanumsquare se-weight-unset\" id=\"SE-91b4e619-967f-47dd-a6b3-07d64d4dfe30\" style=\"color:#555555;\">​</span></p><!-- } SE-TEXT --><!-- SE-TEXT { --><p class=\"se-text-paragraph se-text-paragraph-align-\" id=\"SE-b07c7b18-f412-4c1a-a7ce-77341156020a\" style=\"\"><span class=\"se-fs-fs16 se-ff-nanumsquare se-weight-unset\" id=\"SE-e93f486a-5885-42ec-a139-dbfd1d023c0c\" style=\"color:#555555;\">하지만 고객이 사고 싶은 건 그 정보가 아니라 변화된 모습입니다.</span></p><!-- } SE-TEXT --><!-- SE-TEXT { --><p class=\"se-text-paragraph se-text-paragraph-align-\" id=\"SE-e5560418-907a-4951-937a-156063abc6dd\" style=\"\"><span class=\"se-fs-fs16 se-ff-nanumsquare se-weight-unset\" id=\"SE-6b5876a1-9873-4c3c-a26a-f7062bb4c040\" style=\"color:#555555;\">​</span></p><!-- } SE-TEXT --><!-- SE-TEXT { --><p class=\"se-text-paragraph se-text-paragraph-align-\" id=\"SE-b02cd3b4-daec-4afc-9f13-218ceb48b1df\" style=\"\"><span class=\"se-fs-fs16 se-ff-nanumsquare se-weight-unset\" id=\"SE-d38f1528-4088-456e-b71a-09c1846bf3e7\" style=\"color:#555555;\">기획자가 써야 할 것 실제 많이 쓰는 것</span></p><!-- } SE-TEXT --><!-- SE-TEXT { --><p class=\"se-text-paragraph se-text-paragraph-align-\" id=\"SE-7f53c6cf-0081-42c7-be8d-73772fb207d8\" style=\"\"><span class=\"se-fs-fs16 se-ff-nanumsquare se-weight-unset\" id=\"SE-ef816268-f0af-4adf-bb0b-5d054acd1974\" style=\"color:#555555;\">사용 후 상태 제품 기능</span></p><!-- } SE-TEXT --><!-- SE-TEXT { --><p class=\"se-text-paragraph se-text-paragraph-align-\" id=\"SE-5cc785e8-0151-4b1c-bc67-a0728b702ea4\" style=\"\"><span class=\"se-fs-fs16 se-ff-nanumsquare se-weight-unset\" id=\"SE-a5f66aad-e03c-42da-8880-2c23f28d15dd\" style=\"color:#555555;\">고객의 일상 변화 기술 설명</span></p><!-- } SE-TEXT --><!-- SE-TEXT { --><p class=\"se-text-paragraph se-text-paragraph-align-\" id=\"SE-c16502cd-8200-43aa-82a4-5a88bf19b896\" style=\"\"><span class=\"se-fs-fs16 se-ff-nanumsquare se-weight-unset\" id=\"SE-663fb444-6d7e-4374-a725-5880a79ff9d4\" style=\"color:#555555;\">감정 수치</span></p><!-- } SE-TEXT --><!-- SE-TEXT { --><p class=\"se-text-paragraph se-text-paragraph-align-\" id=\"SE-ad86683b-d12a-4f24-838a-949b837bbd93\" style=\"\"><span class=\"se-fs-fs16 se-ff-nanumsquare se-weight-unset\" id=\"SE-c68b502a-eacd-4540-8ee8-01bbdbe74953\" style=\"color:#555555;\">​</span></p><!-- } SE-TEXT --><!-- SE-TEXT { --><p class=\"se-text-paragraph se-text-paragraph-align-\" id=\"SE-df6de040-93fc-4ee7-837d-1d1788cbd5f9\" style=\"\"><span class=\"se-fs-fs16 se-ff-nanumsquare se-weight-unset\" id=\"SE-2952610b-afac-45b1-8bbb-1ddf8060daf4\" style=\"color:#555555;\">예시)</span></p><!-- } SE-TEXT --><!-- SE-TEXT { --><p class=\"se-text-paragraph se-text-paragraph-align-\" id=\"SE-3ffb9fce-a962-453e-a452-50467f6322a1\" style=\"\"><span class=\"se-fs-fs16 se-ff-nanumsquare se-weight-unset\" id=\"SE-2ac4f7b4-4651-4cbf-baa4-cd450c9aebef\" style=\"color:#ff0010;\">×</span><span class=\"se-fs-fs16 se-ff-nanumsquare se-weight-unset\" id=\"SE-69dcec76-24e5-4f23-8826-a6fc8845ade2\" style=\"color:#555555;\"> “모이스처 라이징 스타일”</span></p><!-- } SE-TEXT -->\n</div>\n</div>\n</div>\n\n</div> <div class=\"se-component se-image se-l-default\" id=\"SE-913dee9e-ef9d-4f09-bdbc-471d1974c67e\">\n<div class=\"se-component-content se-component-content-normal\">\n<div class=\"se-section se-section-image se-l-default se-section-align-\" style=\"max-width:595px;\">\n<div class=\"se-module se-module-image\" style=\"\">\n<a class=\"se-module-image-link __se_image_link __se_link\" data-linkdata='{\"id\" : \"SE-913dee9e-ef9d-4f09-bdbc-471d1974c67e\", \"src\" : \"https://mblogthumb-phinf.pstatic.net/MjAyNjAyMTdfMTcz/MDAxNzcxMzAzNDg3OTk3.1B4YtRNY2Od7U6EhqDKpP39HXi9G0MHpuM6p8bDY5ekg.6jzxABVUxl5W1ejYRaNqOmjtk3o8Znmk6XTFa_ajYiog.PNG/%EC%83%B4%ED%91%B8_008.png\", \"originalWidth\" : \"595\", \"originalHeight\" : \"708\", \"linkUse\" : \"false\", \"link\" : \"\", \"fileSize\": \"486186\" }' data-linktype=\"img\" href=\"#\" onclick=\"return false;\" style=\"\">\n<img alt=\"\" class=\"se-image-resource\" src=\"https://mblogthumb-phinf.pstatic.net/MjAyNjAyMTdfMTcz/MDAxNzcxMzAzNDg3OTk3.1B4YtRNY2Od7U6EhqDKpP39HXi9G0MHpuM6p8bDY5ekg.6jzxABVUxl5W1ejYRaNqOmjtk3o8Znmk6XTFa_ajYiog.PNG/%EC%83%B4%ED%91%B8_008.png?type=w966\"/>\n</a>\n</div>\n</div>\n</div>\n\n</div>\n<div class=\"se-component se-text se-l-default\" id=\"SE-fb06b9f0-d107-4f45-8546-5197791f0e9c\">\n<div class=\"se-component-content\">\n<div class=\"se-section se-section-text se-l-default\">\n<div class=\"se-module se-module-text\">\n<!-- SE-TEXT { --><p class=\"se-text-paragraph se-text-paragraph-align-\" id=\"SE-4bcb1271-b4f9-40f8-99b1-3b7d5a8d6662\" style=\"\"><span class=\"se-fs-fs16 se-ff-nanumsquare se-weight-unset\" id=\"SE-cf6e6b3b-fe0e-4d20-b2b2-2695b6f75fb0\" style=\"color:#555555;\">고객은 읽고 싶은 것만 또는 자신이 필요한 것만 슬쩍 지나가듯 읽습니다. \"</span><span class=\"se-fs-fs16 se-ff-nanumsquare se-weight-unset\" id=\"SE-3a8e1465-d2c0-40c7-be51-f14987297d48\" style=\"color:#ff0010;\">(주)파파스컴퍼니</span><span class=\"se-fs-fs16 se-ff-nanumsquare se-weight-unset\" id=\"SE-a95567d2-1c1e-4eeb-86e8-ee92f92ad59e\" style=\"color:#555555;\">\"이라는 브랜드명과 \"</span><span class=\"se-fs-fs16 se-ff-nanumsquare se-weight-unset\" id=\"SE-dceabc5a-7d32-4c64-92f0-1f7b12e9cfac\" style=\"color:#ff0010;\">모이스처 라이징</span><span class=\"se-fs-fs16 se-ff-nanumsquare se-weight-unset\" id=\"SE-2e750125-d5bb-47ab-8c66-15d89f1770f7\" style=\"color:#555555;\">\"이라는 말은 관심도 없고 고객의 궁금증 유발 사항도 아닙니다.</span></p><!-- } SE-TEXT --><!-- SE-TEXT { --><p class=\"se-text-paragraph se-text-paragraph-align-\" id=\"SE-11c03547-cb74-40ca-bb9e-ebcad3a4dc06\" style=\"\"><span class=\"se-fs-fs16 se-ff-nanumsquare se-weight-unset\" id=\"SE-cf5e844a-8e3e-4939-9a3c-aa2c3c814da0\" style=\"color:#555555;\">​</span></p><!-- } SE-TEXT --><!-- SE-TEXT { --><p class=\"se-text-paragraph se-text-paragraph-align-\" id=\"SE-8f517bb9-2679-45bf-be1e-1950ec568a7a\" style=\"\"><span class=\"se-fs-fs16 se-ff-nanumsquare se-weight-unset\" id=\"SE-bc213561-7127-46a6-8a71-80383e2702b0\" style=\"color:#555555;\">알지도 못하는 브랜드는 이해도 안 될뿐더러 지나가는 그냥 이미지 조작에 불과합니다. 이런 조작은 기억에 남지도 않고 판단의 영역도 아니라는 뜻입니다.</span></p><!-- } SE-TEXT --><!-- SE-TEXT { --><p class=\"se-text-paragraph se-text-paragraph-align-\" id=\"SE-9fdd7942-7a8e-445e-a4c2-4a398d45eee2\" style=\"\"><span class=\"se-fs-fs16 se-ff-nanumsquare se-weight-unset\" id=\"SE-14bd7042-f322-47ca-a600-6ea7e80eb080\" style=\"color:#555555;\">​</span></p><!-- } SE-TEXT --><!-- SE-TEXT { --><p class=\"se-text-paragraph se-text-paragraph-align-\" id=\"SE-f05744d8-754d-470b-8122-dc35f769b484\" style=\"\"><span class=\"se-fs-fs16 se-ff-nanumsquare se-weight-unset\" id=\"SE-c5ff9208-d785-40cd-a3c1-14cfaaaab1dd\" style=\"color:#555555;\">그러므로 </span><span class=\"se-fs-fs19 se-ff-nanumsquare\" id=\"SE-03edc410-8204-4ba8-9049-ebbdca3d2f1d\" style=\"color:#aa1f91;\"><b>히어로 섹션</b></span><span class=\"se-fs-fs16 se-ff-nanumsquare se-weight-unset\" id=\"SE-ed76f123-1bfc-4566-aef9-c0deda0a3e86\" style=\"color:#555555;\">의 영역에서는 절대 이런 표현으로 상세페이지를 만들지 마십시오.</span></p><!-- } SE-TEXT --><!-- SE-TEXT { --><p class=\"se-text-paragraph se-text-paragraph-align-\" id=\"SE-175ce85d-d96b-4ac9-9af0-8c231f49bd80\" style=\"\"><span class=\"se-fs-fs16 se-ff-nanumsquare se-weight-unset\" id=\"SE-0be3864a-3ddc-47de-acd4-ee2deb783d15\" style=\"color:#555555;\">​</span></p><!-- } SE-TEXT --><!-- SE-TEXT { --><p class=\"se-text-paragraph se-text-paragraph-align-\" id=\"SE-d1b252a2-623d-463b-98af-dc1a3218661f\" style=\"\"><span class=\"se-fs-fs16 se-ff-nanumsquare se-weight-unset\" id=\"SE-9ebd31cf-f4a1-4c89-9ab5-3d6eea9b3abc\" style=\"color:#555555;\">​</span></p><!-- } SE-TEXT --><!-- SE-TEXT { --><p class=\"se-text-paragraph se-text-paragraph-align-\" id=\"SE-eac62009-e424-4e67-b0b5-b3e00a21f4e2\" style=\"\"><span class=\"se-fs-fs16 se-ff-nanumsquare se-weight-unset\" id=\"SE-c56602f4-299d-452d-8524-5f4817254ca0\" style=\"color:#555555;\">​</span></p><!-- } SE-TEXT --><!-- SE-TEXT { --><p class=\"se-text-paragraph se-text-paragraph-align-\" id=\"SE-c970b3e6-a359-4a1e-9896-136999153d46\" style=\"\"><span class=\"se-fs-fs16 se-ff-nanumsquare se-weight-unset\" id=\"SE-3908f9b9-3a9c-423d-8c3f-d69fca9a20e8\" style=\"color:#28e1ff;\">○</span><span class=\"se-fs-fs16 se-ff-nanumsquare se-weight-unset\" id=\"SE-79e12cce-83eb-4ce0-a16b-45497f65415f\" style=\"color:#555555;\"> “이거 하나면 충분합니다. 묵은 각질, 한방에 싹!”</span></p><!-- } SE-TEXT -->\n</div>\n</div>\n</div>\n\n</div> <div class=\"se-component se-image se-l-default\" id=\"SE-3ce31eff-e7ec-4265-814f-a473285d9d22\">\n<div class=\"se-component-content se-component-content-normal\">\n<div class=\"se-section se-section-image se-l-default se-section-align-\" style=\"max-width:595px;\">\n<div class=\"se-module se-module-image\" style=\"\">\n<a class=\"se-module-image-link __se_image_link __se_link\" data-linkdata='{\"id\" : \"SE-3ce31eff-e7ec-4265-814f-a473285d9d22\", \"src\" : \"https://mblogthumb-phinf.pstatic.net/MjAyNjAyMTdfMjgg/MDAxNzcxMzAzNDk5MTE5.jMSeno7i21fuTDj3Th4wZpE1_zltMGDbvwYcb44Y0w8g.DCt98cCuIr-YAVN6aO3DMlIeUVczc5byvzT8UWEtz1wg.PNG/%EC%83%B4%ED%91%B8_009.png\", \"originalWidth\" : \"595\", \"originalHeight\" : \"708\", \"linkUse\" : \"false\", \"link\" : \"\", \"fileSize\": \"489639\" }' data-linktype=\"img\" href=\"#\" onclick=\"return false;\" style=\"\">\n<img alt=\"\" class=\"se-image-resource\" src=\"https://mblogthumb-phinf.pstatic.net/MjAyNjAyMTdfMjgg/MDAxNzcxMzAzNDk5MTE5.jMSeno7i21fuTDj3Th4wZpE1_zltMGDbvwYcb44Y0w8g.DCt98cCuIr-YAVN6aO3DMlIeUVczc5byvzT8UWEtz1wg.PNG/%EC%83%B4%ED%91%B8_009.png?type=w966\"/>\n</a>\n</div>\n</div>\n</div>\n\n</div>\n<div class=\"se-component se-text se-l-default\" id=\"SE-d9654f5a-e2a1-4709-bf44-7f3150acd7d7\">\n<div class=\"se-component-content\">\n<div class=\"se-section se-section-text se-l-default\">\n<div class=\"se-module se-module-text\">\n<!-- SE-TEXT { --><p class=\"se-text-paragraph se-text-paragraph-align-\" id=\"SE-ad33f520-c85c-466a-ac42-55a748202f74\" style=\"\"><span class=\"se-fs-fs16 se-ff-nanumsquare se-weight-unset\" id=\"SE-0329927f-a161-4880-a7f0-f7c422bef495\" style=\"color:#555555;\">이 샴푸 상세페이지를 읽는 사람 중에 머리 각질이 심한 분이라면 이 샴푸가 궁금증을 유발하게 될 겁니다. 심지어 브랜드명은 이후 계속 노출되기에 넣지도 않았습니다.</span></p><!-- } SE-TEXT --><!-- SE-TEXT { --><p class=\"se-text-paragraph se-text-paragraph-align-\" id=\"SE-d8585990-ec26-4a76-87bc-831602c79da8\" style=\"\"><span class=\"se-fs-fs16 se-ff-nanumsquare se-weight-unset\" id=\"SE-59acaa33-c032-4d2e-843a-b4783fa2ce88\" style=\"color:#555555;\">​</span></p><!-- } SE-TEXT --><!-- SE-TEXT { --><p class=\"se-text-paragraph se-text-paragraph-align-\" id=\"SE-83ef2fe5-d20f-42f3-bf15-3d5b384f924e\" style=\"\"><span class=\"se-fs-fs16 se-ff-nanumsquare se-weight-unset\" id=\"SE-352a6d9a-9daa-484b-9afa-09cdd4894769\" style=\"color:#555555;\">이 </span><span class=\"se-fs-fs19 se-ff-nanumsquare\" id=\"SE-632d9cfd-0a7a-4fc5-8d02-47557b3d522b\" style=\"color:#aa1f91;\"><b>섹션</b></span><span class=\"se-fs-fs16 se-ff-nanumsquare se-weight-unset\" id=\"SE-0362432e-5332-4662-82fb-48c613523fb9\" style=\"color:#555555;\">에서는 각질을 이 샴푸 하나가 해결한다는 명제만 가지고 갑니다. 그에 따른 성분을 간단하게 노출함으로써 증명의 단계전 신뢰의 단계로만 어필합니다.</span></p><!-- } SE-TEXT --><!-- SE-TEXT { --><p class=\"se-text-paragraph se-text-paragraph-align-\" id=\"SE-a9137bba-cc42-4401-87f1-feabe3cc6706\" style=\"\"><span class=\"se-fs-fs16 se-ff-nanumsquare se-weight-unset\" id=\"SE-75536036-75a0-4ec7-b97b-294b5ca7f160\" style=\"color:#555555;\">​</span></p><!-- } SE-TEXT --><!-- SE-TEXT { --><p class=\"se-text-paragraph se-text-paragraph-align-\" id=\"SE-39198194-fa37-4fe4-a156-4e76b4e7cec7\" style=\"\"><span class=\"se-fs-fs16 se-ff-nanumsquare se-weight-unset\" id=\"SE-26daff56-2cb8-47ca-af08-3a6c07bddf1a\" style=\"color:#555555;\">이처럼 초기 기획에서는 잘한 질문과 그에 맞는 증명이 상세페이지의 핵심이라고 봐도 무방합니다. 이 관점에서 여러분의 상세페이지를 돌아보시기 바랍니다.</span></p><!-- } SE-TEXT --><!-- SE-TEXT { --><p class=\"se-text-paragraph se-text-paragraph-align-\" id=\"SE-5f6a6ac9-26ab-4edf-b871-1dd909b99fd2\" style=\"\"><span class=\"se-fs-fs16 se-ff-nanumsquare se-weight-unset\" id=\"SE-f5b38f31-0295-49be-863d-9d613f8a01bf\" style=\"color:#555555;\">​</span></p><!-- } SE-TEXT --><!-- SE-TEXT { --><p class=\"se-text-paragraph se-text-paragraph-align-\" id=\"SE-975c8983-625d-413e-b54f-611f8286311b\" style=\"\"><span class=\"se-fs-fs16 se-ff-nanumsquare se-weight-unset\" id=\"SE-1bec0990-64a3-40a5-a4c2-9c9ec51d98b3\" style=\"color:#555555;\">이 차이가</span></p><!-- } SE-TEXT --><!-- SE-TEXT { --><p class=\"se-text-paragraph se-text-paragraph-align-\" id=\"SE-299fef30-163d-46ca-bc91-deb36d9f931e\" style=\"\"><span class=\"se-fs-fs19 se-ff-nanumsquare\" id=\"SE-52982eb7-7145-45b4-9b21-fa50db5ef6d2\" style=\"color:#0078cb;\"><b>기획의 차이</b></span><span class=\"se-fs-fs16 se-ff-nanumsquare se-weight-unset\" id=\"SE-b5179dc7-ebe0-4d16-a51e-ba9505248c63\" style=\"color:#555555;\">입니다.</span></p><!-- } SE-TEXT -->\n</div>\n</div>\n</div>\n\n</div> <div class=\"se-component se-horizontalLine se-l-default\" id=\"SE-8a9d093b-0c85-4ca8-805c-f9e40bd546d0\">\n<div class=\"se-component-content\">\n<div class=\"se-section se-section-horizontalLine se-l-default se-section-align-\">\n<div class=\"se-module se-module-horizontalLine\">\n<hr class=\"se-hr\"/>\n</div>\n</div>\n</div>\n</div> <div class=\"se-component se-text se-l-default\" id=\"SE-d88f08eb-4136-4f18-ab0b-53989e332a9b\">\n<div class=\"se-component-content\">\n<div class=\"se-section se-section-text se-l-default\">\n<div class=\"se-module se-module-text\">\n<!-- SE-TEXT { --><p class=\"se-text-paragraph se-text-paragraph-align-\" id=\"SE-57eb82bb-f777-46de-9ebc-a46ec47c506a\" style=\"\"><span class=\"se-fs-fs19 se-ff-nanumsquare se-weight-unset\" id=\"SE-9252c48f-8c35-42f3-b868-13d4d6a5c324\" style=\"color:#0078cb;\">■ 상세페이지 기획의 핵심 구조</span></p><!-- } SE-TEXT --><!-- SE-TEXT { --><p class=\"se-text-paragraph se-text-paragraph-align-\" id=\"SE-c3105679-a638-45fd-a555-16d04c660707\" style=\"\"><span class=\"se-fs-fs16 se-ff-nanumsquare se-weight-unset\" id=\"SE-ae7f9646-480b-42c3-9291-93503a704852\" style=\"color:#555555;\">​</span></p><!-- } SE-TEXT --><!-- SE-TEXT { --><p class=\"se-text-paragraph se-text-paragraph-align-\" id=\"SE-c0591b67-23b2-4c38-9aae-b3375a96ddb9\" style=\"\"><span class=\"se-fs-fs16 se-ff-nanumsquare se-weight-unset\" id=\"SE-195913a1-7a26-4dc4-893e-0b4f57090fc3\" style=\"color:#555555;\">잘 팔리는 상세페이지는 항상 같은 흐름을 가집니다.</span></p><!-- } SE-TEXT --><!-- SE-TEXT { --><p class=\"se-text-paragraph se-text-paragraph-align-\" id=\"SE-4a88fa39-7bc7-4dd1-bb10-315415fde679\" style=\"\"><span class=\"se-fs-fs16 se-ff-nanumsquare se-weight-unset\" id=\"SE-3c56bf67-45ca-4183-a512-b9c0d5429f48\" style=\"color:#555555;\">​</span></p><!-- } SE-TEXT --><!-- SE-TEXT { --><p class=\"se-text-paragraph se-text-paragraph-align-\" id=\"SE-edf99f11-69d5-4337-a4c6-92181d196ca8\" style=\"\"><span class=\"se-fs-fs16 se-ff-nanumsquare se-weight-unset\" id=\"SE-4163896a-c108-430c-9a87-d220308509bd\" style=\"color:#555555;\">문제 제시</span></p><!-- } SE-TEXT --><!-- SE-TEXT { --><p class=\"se-text-paragraph se-text-paragraph-align-\" id=\"SE-50ae05e7-0d8e-41c6-aa74-e65763e62ea9\" style=\"\"><span class=\"se-fs-fs16 se-ff-nanumsquare se-weight-unset\" id=\"SE-fd15cf56-2581-4e0f-94f4-c8499e1408c7\" style=\"color:#555555;\">→ 공감</span></p><!-- } SE-TEXT --><!-- SE-TEXT { --><p class=\"se-text-paragraph se-text-paragraph-align-\" id=\"SE-c7af9d67-5ae2-4b15-be03-a683c73593fb\" style=\"\"><span class=\"se-fs-fs16 se-ff-nanumsquare se-weight-unset\" id=\"SE-7dde6c4d-2a3b-4510-b8c2-00f7b8955b7d\" style=\"color:#555555;\">→ 해결책 제안</span></p><!-- } SE-TEXT --><!-- SE-TEXT { --><p class=\"se-text-paragraph se-text-paragraph-align-\" id=\"SE-fa4dd624-1cc4-4e26-955b-07f95b674508\" style=\"\"><span class=\"se-fs-fs16 se-ff-nanumsquare se-weight-unset\" id=\"SE-ce780fa6-d43e-44e4-9045-29bdefa33f03\" style=\"color:#555555;\">→ 제품 등장</span></p><!-- } SE-TEXT --><!-- SE-TEXT { --><p class=\"se-text-paragraph se-text-paragraph-align-\" id=\"SE-f7d0852a-5a75-4d33-b200-73adf83cde06\" style=\"\"><span class=\"se-fs-fs16 se-ff-nanumsquare se-weight-unset\" id=\"SE-a775b2d3-518d-438f-9d2a-0d05912cfdf7\" style=\"color:#555555;\">→ 신뢰</span></p><!-- } SE-TEXT --><!-- SE-TEXT { --><p class=\"se-text-paragraph se-text-paragraph-align-\" id=\"SE-9b86d100-fab0-435d-bac2-ef95952ccd21\" style=\"\"><span class=\"se-fs-fs16 se-ff-nanumsquare se-weight-unset\" id=\"SE-ae28a052-6942-4401-a984-cd037711150a\" style=\"color:#555555;\">→ 행동 유도</span></p><!-- } SE-TEXT --><!-- SE-TEXT { --><p class=\"se-text-paragraph se-text-paragraph-align-\" id=\"SE-cbbf6c0b-2c4c-4eb9-ac95-bac074b1bdd1\" style=\"\"><span class=\"se-fs-fs16 se-ff-nanumsquare se-weight-unset\" id=\"SE-af4f5556-1390-4f1e-94c1-6fca017a192d\" style=\"color:#555555;\">​</span></p><!-- } SE-TEXT --><!-- SE-TEXT { --><p class=\"se-text-paragraph se-text-paragraph-align-\" id=\"SE-30b7e34d-62ff-4444-b900-e951a0b019bb\" style=\"\"><span class=\"se-fs-fs16 se-ff-nanumsquare se-weight-unset\" id=\"SE-861fcd34-1672-4471-8e4b-fe4b3bd0f8c9\" style=\"color:#555555;\">이 순서를 바꾸는 순간 이탈률이 올라갑니다.</span></p><!-- } SE-TEXT --><!-- SE-TEXT { --><p class=\"se-text-paragraph se-text-paragraph-align-\" id=\"SE-d70c7733-e38b-4782-8775-f47af5bfbebd\" style=\"\"><span class=\"se-fs-fs16 se-ff-nanumsquare se-weight-unset\" id=\"SE-9610e936-a7e0-4dd6-b82d-acfd8b147ed2\" style=\"color:#555555;\">​</span></p><!-- } SE-TEXT --><!-- SE-TEXT { --><p class=\"se-text-paragraph se-text-paragraph-align-\" id=\"SE-9869651e-d49c-4545-a051-3d71a2d75166\" style=\"\"><span class=\"se-fs-fs16 se-ff-nanumsquare se-weight-unset\" id=\"SE-dacc3380-4685-4e8d-a1f2-ae58e7014071\" style=\"color:#555555;\">기획자는</span></p><!-- } SE-TEXT --><!-- SE-TEXT { --><p class=\"se-text-paragraph se-text-paragraph-align-\" id=\"SE-2cee9afe-4145-4e54-8f83-abc23a310ae9\" style=\"\"><span class=\"se-fs-fs16 se-ff-nanumsquare\" id=\"SE-deb15756-87ff-464c-91bd-5ee266e25907\" style=\"color:#ff0010;\"><b>“여기에 뭘 넣을까?”</b></span><span class=\"se-fs-fs16 se-ff-nanumsquare se-weight-unset\" id=\"SE-130c9e2e-5467-4272-8044-0fff2775c8c0\" style=\"color:#555555;\">가 아니라</span></p><!-- } SE-TEXT --><!-- SE-TEXT { --><p class=\"se-text-paragraph se-text-paragraph-align-\" id=\"SE-014041bc-bca4-46b3-897f-fd3a54b92aed\" style=\"\"><span class=\"se-fs-fs16 se-ff-nanumsquare\" id=\"SE-6b1d4f0b-f08e-49f4-8064-3ec785f2c434\" style=\"color:#0078cb;\"><b>“지금 고객은 무슨 생각을 할까?”</b></span><span class=\"se-fs-fs16 se-ff-nanumsquare se-weight-unset\" id=\"SE-1913fd2e-fa7c-432b-9b17-9c7bd9b1b399\" style=\"color:#555555;\">를 먼저 고민해야 합니다.</span></p><!-- } SE-TEXT --><!-- SE-TEXT { --><p class=\"se-text-paragraph se-text-paragraph-align-\" id=\"SE-8a496528-1895-47e8-9f5f-9d1684e8f324\" style=\"\"><span class=\"se-fs-fs16 se-ff-nanumsquare se-weight-unset\" id=\"SE-0ab31251-0191-4a33-a40c-798c723ea64e\" style=\"color:#555555;\">​</span></p><!-- } SE-TEXT -->\n</div>\n</div>\n</div>\n\n</div> <div class=\"se-component se-image se-l-default\" id=\"SE-158ba03f-3d01-497f-948f-189a4d00847e\">\n<div class=\"se-component-content se-component-content-fit\">\n<div class=\"se-section se-section-image se-l-default se-section-align-\">\n<div class=\"se-module se-module-image\" style=\"\">\n<a class=\"se-module-image-link __se_image_link __se_link\" data-linkdata='{\"id\" : \"SE-158ba03f-3d01-497f-948f-189a4d00847e\", \"src\" : \"https://mblogthumb-phinf.pstatic.net/MjAyNjAyMTdfMjYg/MDAxNzcxMzA2NzkyODk3.raTeMYBMg7oGzivpTFaP9C0BiQBmzi5sxnRof--p8VAg.3G4bw_wtFjNaTxMz128OuOAN9XHpwMaTearXyBmXCOUg.PNG/%EC%83%B4%ED%91%B8_013.png\", \"originalWidth\" : \"595\", \"originalHeight\" : \"491\", \"linkUse\" : \"false\", \"link\" : \"\", \"fileSize\": \"341474\" }' data-linktype=\"img\" href=\"#\" onclick=\"return false;\" style=\"\">\n<img alt=\"\" class=\"se-image-resource\" src=\"https://mblogthumb-phinf.pstatic.net/MjAyNjAyMTdfMjYg/MDAxNzcxMzA2NzkyODk3.raTeMYBMg7oGzivpTFaP9C0BiQBmzi5sxnRof--p8VAg.3G4bw_wtFjNaTxMz128OuOAN9XHpwMaTearXyBmXCOUg.PNG/%EC%83%B4%ED%91%B8_013.png?type=w966\"/>\n</a>\n</div>\n</div>\n</div>\n\n</div>\n<div class=\"se-component se-image se-l-default\" id=\"SE-0a311240-b9a4-4606-881e-f10dce127e2c\">\n<div class=\"se-component-content se-component-content-normal\">\n<div class=\"se-section se-section-image se-l-default se-section-align-\" style=\"max-width:595px;\">\n<div class=\"se-module se-module-image\" style=\"\">\n<a class=\"se-module-image-link __se_image_link __se_link\" data-linkdata='{\"id\" : \"SE-0a311240-b9a4-4606-881e-f10dce127e2c\", \"src\" : \"https://mblogthumb-phinf.pstatic.net/MjAyNjAyMTdfMTk3/MDAxNzcxMzA2MjAxMTE3.itZYIr60QrJNiC0RWRAZ_ONxPujZFXef7MxL7eGsW3gg.5iUFQ-ZgvcnZNy_2mL-us_9KfsNsnBdxUtVgRgh1ztAg.PNG/%EC%83%B4%ED%91%B8_011.png\", \"originalWidth\" : \"595\", \"originalHeight\" : \"849\", \"linkUse\" : \"false\", \"link\" : \"\", \"fileSize\": \"493438\" }' data-linktype=\"img\" href=\"#\" onclick=\"return false;\" style=\"\">\n<img alt=\"\" class=\"se-image-resource\" src=\"https://mblogthumb-phinf.pstatic.net/MjAyNjAyMTdfMTk3/MDAxNzcxMzA2MjAxMTE3.itZYIr60QrJNiC0RWRAZ_ONxPujZFXef7MxL7eGsW3gg.5iUFQ-ZgvcnZNy_2mL-us_9KfsNsnBdxUtVgRgh1ztAg.PNG/%EC%83%B4%ED%91%B8_011.png?type=w966\"/>\n</a>\n</div>\n</div>\n</div>\n\n</div>\n<div class=\"se-component se-image se-l-default\" id=\"SE-e4d2a3b9-1abe-4759-80d9-953bd3b6ce9b\">\n<div class=\"se-component-content se-component-content-normal\">\n<div class=\"se-section se-section-image se-l-default se-section-align-\" style=\"max-width:595px;\">\n<div class=\"se-module se-module-image\" style=\"\">\n<a class=\"se-module-image-link __se_image_link __se_link\" data-linkdata='{\"id\" : \"SE-e4d2a3b9-1abe-4759-80d9-953bd3b6ce9b\", \"src\" : \"https://mblogthumb-phinf.pstatic.net/MjAyNjAyMTdfNTMg/MDAxNzcxMzA2NDc4NTU4.5tIIzPlSrPTWUjDSv7fulaoPCqrQGumNgUfmyDB1GPgg.haWwT-xjfrr98OTsM9foEN4Uo-UlnFHmcI2lVeA-hJ4g.PNG/%EC%83%B4%ED%91%B8_012.png\", \"originalWidth\" : \"595\", \"originalHeight\" : \"849\", \"linkUse\" : \"false\", \"link\" : \"\", \"fileSize\": \"501620\" }' data-linktype=\"img\" href=\"#\" onclick=\"return false;\" style=\"\">\n<img alt=\"\" class=\"se-image-resource\" src=\"https://mblogthumb-phinf.pstatic.net/MjAyNjAyMTdfNTMg/MDAxNzcxMzA2NDc4NTU4.5tIIzPlSrPTWUjDSv7fulaoPCqrQGumNgUfmyDB1GPgg.haWwT-xjfrr98OTsM9foEN4Uo-UlnFHmcI2lVeA-hJ4g.PNG/%EC%83%B4%ED%91%B8_012.png?type=w966\"/>\n</a>\n</div>\n</div>\n</div>\n\n</div>\n<div class=\"se-component se-horizontalLine se-l-default\" id=\"SE-d1ac4bd1-2bd6-4cc8-9f70-291a042911e7\">\n<div class=\"se-component-content\">\n<div class=\"se-section se-section-horizontalLine se-l-default se-section-align-\">\n<div class=\"se-module se-module-horizontalLine\">\n<hr class=\"se-hr\"/>\n</div>\n</div>\n</div>\n</div> <div class=\"se-component se-text se-l-default\" id=\"SE-6aebd551-6a0f-449a-b029-d8382341515f\">\n<div class=\"se-component-content\">\n<div class=\"se-section se-section-text se-l-default\">\n<div class=\"se-module se-module-text\">\n<!-- SE-TEXT { --><p class=\"se-text-paragraph se-text-paragraph-align-\" id=\"SE-1ec31b22-6c92-4f46-be16-61f2cd875be3\" style=\"\"><span class=\"se-fs-fs19 se-ff-nanumsquare se-weight-unset\" id=\"SE-069fcb97-591b-4495-90ce-62f5e65d4b9d\" style=\"color:#0078cb;\">■ 기획이 된 상세페이지 vs 안 된 상세페이지</span></p><!-- } SE-TEXT --><!-- SE-TEXT { --><p class=\"se-text-paragraph se-text-paragraph-align-\" id=\"SE-fefd31a5-0bfe-4af2-93d6-af237536e648\" style=\"\"><span class=\"se-fs-fs16 se-ff-nanumsquare se-weight-unset\" id=\"SE-76675e9d-8b5a-4107-aa84-d06aee22f00e\" style=\"color:#555555;\">​</span></p><!-- } SE-TEXT --><!-- SE-TEXT { --><p class=\"se-text-paragraph se-text-paragraph-align-\" id=\"SE-39801f64-c80d-4e6a-8498-f23c4f66f123\" style=\"\"><span class=\"se-fs-fs16 se-ff-nanumsquare\" id=\"SE-e163ab6a-e661-4fee-a5d7-b7f217979897\" style=\"color:#ff0010;\"><b>×</b></span><span class=\"se-fs-fs16 se-ff-nanumsquare\" id=\"SE-4d312f9f-8f67-4298-9b99-fe7b6e8e1404\" style=\"color:#555555;\"><b> 기획 없는 상세페이지</b></span></p><!-- } SE-TEXT --><!-- SE-TEXT { --><p class=\"se-text-paragraph se-text-paragraph-align-\" id=\"SE-ca312437-a518-4ecc-b7f4-7c4b31d0d2c9\" style=\"\"><span class=\"se-fs-fs16 se-ff-nanumsquare se-weight-unset\" id=\"SE-8e8170db-4a48-4478-9ba0-991b2c4da549\" style=\"color:#555555;\">· 정보는 많음</span></p><!-- } SE-TEXT --><!-- SE-TEXT { --><p class=\"se-text-paragraph se-text-paragraph-align-\" id=\"SE-f8cdd9de-2378-4861-9815-0f7e68f2d7a9\" style=\"\"><span class=\"se-fs-fs16 se-ff-nanumsquare se-weight-unset\" id=\"SE-3429b21b-4a52-46dc-b263-bc4139124f83\" style=\"color:#555555;\">· 하지만 기억에 남지 않음</span></p><!-- } SE-TEXT --><!-- SE-TEXT { --><p class=\"se-text-paragraph se-text-paragraph-align-\" id=\"SE-ee4f876d-dc8e-4a4c-be77-b9b1d68cf265\" style=\"\"><span class=\"se-fs-fs16 se-ff-nanumsquare se-weight-unset\" id=\"SE-e3d47cd9-cc6f-42d6-b82b-2b51a65da3cd\" style=\"color:#555555;\">· 가격 비교만 하고 나감</span></p><!-- } SE-TEXT --><!-- SE-TEXT { --><p class=\"se-text-paragraph se-text-paragraph-align-\" id=\"SE-2e3daf6b-3ce9-408f-b604-41b30684c908\" style=\"\"><span class=\"se-fs-fs16 se-ff-nanumsquare se-weight-unset\" id=\"SE-be838c29-54d7-4ce5-b0e4-7a9ad488b546\" style=\"color:#555555;\">​</span></p><!-- } SE-TEXT --><!-- SE-TEXT { --><p class=\"se-text-paragraph se-text-paragraph-align-\" id=\"SE-1cb83f16-c937-49b0-9fcb-a4b2d9993bb8\" style=\"\"><span class=\"se-fs-fs16 se-ff-nanumsquare\" id=\"SE-0ee40442-b4f5-4d88-954f-fa15d1c4e9b1\" style=\"color:#28e1ff;\"><b>○</b></span><span class=\"se-fs-fs16 se-ff-nanumsquare\" id=\"SE-8d017903-272e-4102-b6ee-8896752489d2\" style=\"color:#555555;\"><b> 기획된 상세페이지</b></span></p><!-- } SE-TEXT --><!-- SE-TEXT { --><p class=\"se-text-paragraph se-text-paragraph-align-\" id=\"SE-11fc6b73-b318-44dc-bcc9-80658b5d2c02\" style=\"\"><span class=\"se-fs-fs16 se-ff-nanumsquare se-weight-unset\" id=\"SE-6eb7e8db-96f9-4f37-a63b-cdb479fca4af\" style=\"color:#555555;\">· 처음부터 끝까지 읽게 됨</span></p><!-- } SE-TEXT --><!-- SE-TEXT { --><p class=\"se-text-paragraph se-text-paragraph-align-\" id=\"SE-f0658406-6bd4-433a-af62-79a990fcc211\" style=\"\"><span class=\"se-fs-fs16 se-ff-nanumsquare se-weight-unset\" id=\"SE-b198def6-181c-4492-976d-c01a01ab2f8c\" style=\"color:#555555;\">· 제품이 이해됨</span></p><!-- } SE-TEXT --><!-- SE-TEXT { --><p class=\"se-text-paragraph se-text-paragraph-align-\" id=\"SE-e609d464-e0e1-440b-a78c-2cb9d7b1148f\" style=\"\"><span class=\"se-fs-fs16 se-ff-nanumsquare se-weight-unset\" id=\"SE-9ca38268-ddef-4ed0-98b5-0a82abcf2f15\" style=\"color:#555555;\">· ‘사야 할 이유’가 남음</span></p><!-- } SE-TEXT -->\n</div>\n</div>\n</div>\n\n</div> <div class=\"se-component se-horizontalLine se-l-default\" id=\"SE-cd268999-6d14-434f-b79a-a18ed0b0ffbc\">\n<div class=\"se-component-content\">\n<div class=\"se-section se-section-horizontalLine se-l-default se-section-align-\">\n<div class=\"se-module se-module-horizontalLine\">\n<hr class=\"se-hr\"/>\n</div>\n</div>\n</div>\n</div> <div class=\"se-component se-text se-l-default\" id=\"SE-aaa9064b-5fdd-4776-b402-4c862b88ed52\">\n<div class=\"se-component-content\">\n<div class=\"se-section se-section-text se-l-default\">\n<div class=\"se-module se-module-text\">\n<!-- SE-TEXT { --><p class=\"se-text-paragraph se-text-paragraph-align-\" id=\"SE-6f03aa22-060e-4d5b-983c-a1b6329217f6\" style=\"\"><span class=\"se-fs-fs19 se-ff-nanumsquare se-weight-unset\" id=\"SE-c7c53e4f-2d9c-4191-b40a-1e8c2a12bf7b\" style=\"color:#0078cb;\">■ 상세페이지 기획자의 역할</span></p><!-- } SE-TEXT --><!-- SE-TEXT { --><p class=\"se-text-paragraph se-text-paragraph-align-\" id=\"SE-e919a6d4-7481-4b2d-8e5a-76f31e1d8fc4\" style=\"\"><span class=\"se-fs-fs16 se-ff-nanumsquare se-weight-unset\" id=\"SE-e40cc7fd-7a1f-4166-8f07-e250457e1c4f\" style=\"color:#555555;\">​</span></p><!-- } SE-TEXT --><!-- SE-TEXT { --><p class=\"se-text-paragraph se-text-paragraph-align-\" id=\"SE-f362a908-7ca0-433b-b41b-9c30df1b3f87\" style=\"\"><span class=\"se-fs-fs16 se-ff-nanumsquare se-weight-unset\" id=\"SE-2b697a0d-c894-4e3f-969e-71dce764f761\" style=\"color:#555555;\">기획자는</span></p><!-- } SE-TEXT --><!-- SE-TEXT { --><p class=\"se-text-paragraph se-text-paragraph-align-\" id=\"SE-dc9151a6-f680-4f3c-8f04-ac3196b7ea16\" style=\"\"><span class=\"se-fs-fs16 se-ff-nanumsquare se-weight-unset\" id=\"SE-e013a501-f665-44cb-91de-859891dab7dc\" style=\"color:#555555;\">디자이너도, 카피라이터도 아닙니다.</span></p><!-- } SE-TEXT --><!-- SE-TEXT { --><p class=\"se-text-paragraph se-text-paragraph-align-\" id=\"SE-d155fafb-de12-4e52-8a54-0ada0e51e1af\" style=\"\"><span class=\"se-fs-fs16 se-ff-nanumsquare se-weight-unset\" id=\"SE-009e68dd-6040-412b-a6c6-f59856d48e0f\" style=\"color:#555555;\">​</span></p><!-- } SE-TEXT --><!-- SE-TEXT { --><p class=\"se-text-paragraph se-text-paragraph-align-\" id=\"SE-fbb519be-26ec-4f99-b397-7d9e35404ade\" style=\"\"><span class=\"se-fs-fs16 se-ff-nanumsquare se-weight-unset\" id=\"SE-dfcdf59c-028f-4cbb-bc37-53af0ccca974\" style=\"color:#555555;\">\"</span><span class=\"se-fs-fs19 se-ff-nanumsquare\" id=\"SE-982faa6b-7f5f-41cd-9335-a730355901c0\" style=\"color:#aa1f91;\"><b>고객의 머릿속을 대신 정리해 주는 사람</b></span><span class=\"se-fs-fs16 se-ff-nanumsquare se-weight-unset\" id=\"SE-d824aea3-6d15-4c48-833e-70428d8825fd\" style=\"color:#555555;\">\"입니다.</span></p><!-- } SE-TEXT --><!-- SE-TEXT { --><p class=\"se-text-paragraph se-text-paragraph-align-\" id=\"SE-6d48efbf-e5b2-4668-8559-bedeee8b5db9\" style=\"\"><span class=\"se-fs-fs16 se-ff-nanumsquare se-weight-unset\" id=\"SE-f9c65d72-c954-4a98-9a33-5ee5bb398798\" style=\"color:#555555;\">​</span></p><!-- } SE-TEXT --><!-- SE-TEXT { --><p class=\"se-text-paragraph se-text-paragraph-align-\" id=\"SE-bbf71062-4354-479a-8a0a-5081a1ca7611\" style=\"\"><span class=\"se-fs-fs16 se-ff-nanumsquare se-weight-unset\" id=\"SE-a62b4b43-4ad2-457b-b25f-b4c3e48ff1d9\" style=\"color:#555555;\">고객이 이렇게 생각하게 만드는 게 목표입니다.</span></p><!-- } SE-TEXT --><!-- SE-TEXT { --><p class=\"se-text-paragraph se-text-paragraph-align-\" id=\"SE-dd406aa5-a48d-4d95-9baf-8c195e410583\" style=\"\"><span class=\"se-fs-fs16 se-ff-nanumsquare se-weight-unset\" id=\"SE-01af7570-4984-430c-89a6-4f1539e546fc\" style=\"color:#555555;\">​</span></p><!-- } SE-TEXT --><!-- SE-TEXT { --><p class=\"se-text-paragraph se-text-paragraph-align-\" id=\"SE-91ebdd03-5e0c-48fb-8456-533fa1866515\" style=\"\"><span class=\"se-fs-fs16 se-ff-nanumsquare\" id=\"SE-8843574f-78b0-4b96-be0a-b5baed62d0ac\" style=\"color:#28e1ff;\"><b>○ </b></span><span class=\"se-fs-fs16 se-ff-nanumsquare se-weight-unset\" id=\"SE-4e327695-f92f-422e-bb21-d3b8b7e71381\" style=\"color:#555555;\">“아… 그래서 이걸 사야 하는구나.”</span></p><!-- } SE-TEXT -->\n</div>\n</div>\n</div>\n\n</div> <div class=\"se-component se-horizontalLine se-l-default\" id=\"SE-1b0284ef-e9a3-4022-974d-50288a44fcf2\">\n<div class=\"se-component-content\">\n<div class=\"se-section se-section-horizontalLine se-l-default se-section-align-\">\n<div class=\"se-module se-module-horizontalLine\">\n<hr class=\"se-hr\"/>\n</div>\n</div>\n</div>\n</div> <div class=\"se-component se-text se-l-default\" id=\"SE-ce16cbd0-3c85-42d2-b8f9-747cd8b24a8c\">\n<div class=\"se-component-content\">\n<div class=\"se-section se-section-text se-l-default\">\n<div class=\"se-module se-module-text\">\n<!-- SE-TEXT { --><p class=\"se-text-paragraph se-text-paragraph-align-\" id=\"SE-58a16392-fcf0-4e56-980e-4c273e32795f\" style=\"\"><span class=\"se-fs-fs19 se-ff-nanumsquare se-weight-unset\" id=\"SE-8e90c71b-c03a-466b-8d4e-92b179b80f98\" style=\"color:#0078cb;\">■ 결론</span></p><!-- } SE-TEXT --><!-- SE-TEXT { --><p class=\"se-text-paragraph se-text-paragraph-align-\" id=\"SE-616f8e9b-e569-4d91-9d09-284529f9e11c\" style=\"\"><span class=\"se-fs-fs16 se-ff-nanumsquare se-weight-unset\" id=\"SE-17f994af-b38c-447a-9815-19ec3052c0c4\" style=\"color:#555555;\">​</span></p><!-- } SE-TEXT --><!-- SE-TEXT { --><p class=\"se-text-paragraph se-text-paragraph-align-\" id=\"SE-8eb7788f-8551-4243-ada3-072282d56e65\" style=\"\"><span class=\"se-fs-fs16 se-ff-nanumsquare se-weight-unset\" id=\"SE-b13d9858-48d0-47d4-a5dc-3d6380921ea7\" style=\"color:#555555;\">상세페이지는 디자인으로 완성되는 게 아니라 기획으로 성패가 갈립니다.</span></p><!-- } SE-TEXT --><!-- SE-TEXT { --><p class=\"se-text-paragraph se-text-paragraph-align-\" id=\"SE-9d6bcba6-3ad6-4cf3-9d65-436b1071931d\" style=\"\"><span class=\"se-fs-fs16 se-ff-nanumsquare se-weight-unset\" id=\"SE-f0c9a814-b423-490d-9396-aef178032108\" style=\"color:#555555;\">​</span></p><!-- } SE-TEXT --><!-- SE-TEXT { --><p class=\"se-text-paragraph se-text-paragraph-align-\" id=\"SE-79ceb79a-fc86-4246-9901-e40460820dbb\" style=\"\"><span class=\"se-fs-fs16 se-ff-nanumsquare se-weight-unset\" id=\"SE-2fd49a78-8eb6-410c-bb0a-5a8068de6049\" style=\"color:#555555;\">기획 없는 디자인은 예쁜 포스터일 뿐이고, 기획이 있는 상세페이지는 24시간 일하는 영업사원입니다.</span></p><!-- } SE-TEXT --><!-- SE-TEXT { --><p class=\"se-text-paragraph se-text-paragraph-align-\" id=\"SE-fe470022-7045-455d-b4b3-e11e2e5ac69e\" style=\"\"><span class=\"se-fs-fs16 se-ff-nanumsquare se-weight-unset\" id=\"SE-cddf15ae-dcd2-40f6-b5d4-21a364c91e23\" style=\"color:#555555;\">​</span></p><!-- } SE-TEXT --><!-- SE-TEXT { --><p class=\"se-text-paragraph se-text-paragraph-align-\" id=\"SE-0b47e339-85dc-42c4-a6aa-8e351f4b7155\" style=\"\"><span class=\"se-fs-fs16 se-ff-nanumsquare\" id=\"SE-bddbe81e-aab6-4d6c-89d3-5d4b93bcf0f0\" style=\"color:#004e82;background-color:#fff8b2;\"><b>○ </b></span><span class=\"se-fs-fs16 se-ff-nanumsquare se-weight-unset\" id=\"SE-68512cb8-c3ea-43fb-bec2-642c33753820\" style=\"color:#004e82;background-color:#fff8b2;\">“상세페이지의 절반은 기획에서 이미 끝난다.”</span></p><!-- } SE-TEXT -->\n</div>\n</div>\n</div>\n\n</div> <div class=\"se-component se-horizontalLine se-l-line1\" id=\"SE-e434fcbc-3952-4db3-a28a-60034757c2e2\">\n<div class=\"se-component-content\">\n<div class=\"se-section se-section-horizontalLine se-l-line1 se-section-align-\">\n<div class=\"se-module se-module-horizontalLine\">\n<hr class=\"se-hr\"/>\n</div>\n</div>\n</div>\n</div> <div class=\"se-component se-text se-l-default\" id=\"SE-a1691cd1-58bb-4259-9ee8-034883352ed5\">\n<div class=\"se-component-content\">\n<div class=\"se-section se-section-text se-l-default\">\n<div class=\"se-module se-module-text\">\n<!-- SE-TEXT { --><p class=\"se-text-paragraph se-text-paragraph-align-\" id=\"SE-67e19fcd-7c85-4fc8-8c2c-fbf1459191d9\" style=\"\"><span class=\"se-fs-fs19 se-ff-nanumsquare\" id=\"SE-c04d142c-ffd7-49b2-a5bb-f5d5940d91e6\" style=\"color:#004e82;background-color:#ffe3c8;\"><b>이제 </b></span><span class=\"se-fs-fs19 se-ff-nanumsquare\" id=\"SE-d6d23cc0-64e5-4c18-89c1-99bf5dc5eb23\" style=\"color:#ff0010;background-color:#ffe3c8;\"><b>(주)파파스컴퍼니</b></span><span class=\"se-fs-fs19 se-ff-nanumsquare\" id=\"SE-af3043bf-2a3d-4884-8c83-bdac0474b7d4\" style=\"color:#004e82;background-color:#ffe3c8;\"><b>이 가장 잘하는 상세페이지 기획에 대해 알려드립니다.</b></span></p><!-- } SE-TEXT -->\n</div>\n</div>\n</div>\n\n</div> <div class=\"se-component se-image se-l-default\" id=\"SE-5928abed-628a-4d0d-b782-102903b379dd\">\n<div class=\"se-component-content se-component-content-normal\">\n<div class=\"se-section se-section-image se-l-default se-section-align-\" style=\"max-width:595px;\">\n<div class=\"se-module se-module-image\" style=\"\">\n<a class=\"se-module-image-link __se_image_link __se_link\" data-linkdata='{\"id\" : \"SE-5928abed-628a-4d0d-b782-102903b379dd\", \"src\" : \"https://mblogthumb-phinf.pstatic.net/MjAyNjAyMTdfMTc2/MDAxNzcxMzA4MzIwNjA5.SsH8biqc7v-iORLzKWoRSAuuw2FG-s6xZ08FDMvcKJEg.ZpDp4mFdDHT7XUNuaf0bqvgu1AXYJqpqAgK-7uvGCrQg.PNG/%EC%83%B4%ED%91%B8_015.png\", \"originalWidth\" : \"595\", \"originalHeight\" : \"595\", \"linkUse\" : \"false\", \"link\" : \"\", \"fileSize\": \"43042\" }' data-linktype=\"img\" href=\"#\" onclick=\"return false;\" style=\"\">\n<img alt=\"\" class=\"se-image-resource\" src=\"https://mblogthumb-phinf.pstatic.net/MjAyNjAyMTdfMTc2/MDAxNzcxMzA4MzIwNjA5.SsH8biqc7v-iORLzKWoRSAuuw2FG-s6xZ08FDMvcKJEg.ZpDp4mFdDHT7XUNuaf0bqvgu1AXYJqpqAgK-7uvGCrQg.PNG/%EC%83%B4%ED%91%B8_015.png?type=w966\"/>\n</a>\n</div>\n</div>\n</div>\n\n</div>\n<div class=\"se-component se-text se-l-default\" id=\"SE-e25644c5-916b-44c1-a285-9d11788285b9\">\n<div class=\"se-component-content\">\n<div class=\"se-section se-section-text se-l-default\">\n<div class=\"se-module se-module-text\">\n<!-- SE-TEXT { --><p class=\"se-text-paragraph se-text-paragraph-align-\" id=\"SE-0483a0e7-6e69-497a-889b-9876d2ae9e7e\" style=\"\"><span class=\"se-fs-fs16 se-ff-nanumsquare se-weight-unset\" id=\"SE-af1559c4-66e9-4336-80c2-17a5b1cb7372\" style=\"color:#555555;\">​</span></p><!-- } SE-TEXT --><!-- SE-TEXT { --><p class=\"se-text-paragraph se-text-paragraph-align-\" id=\"SE-756f0b6c-c6ff-48a5-955d-d11e01b53587\" style=\"\"><span class=\"se-fs-fs19 se-ff-nanumsquare se-weight-unset\" id=\"SE-661eee2a-9b5e-423d-9891-d16820a77191\" style=\"color:#0078cb;\">■ (주)파파스컴퍼니에 의뢰하면 상세페이지 제작, 매출이 달라지는 이유</span><span class=\"se-fs-fs19 se-ff-nanumsquare se-weight-unset\" id=\"SE-be6ceac5-8888-4ca3-a669-ddb422353bdf\" style=\"color:#0078cb;\">​</span></p><!-- } SE-TEXT --><!-- SE-TEXT { --><p class=\"se-text-paragraph se-text-paragraph-align-\" id=\"SE-07631d34-ffb8-425a-a1c3-a4467a59d5f3\" style=\"\"><span class=\"se-fs-fs16 se-ff-nanumsquare se-weight-unset\" id=\"SE-439a4c9f-91d7-4b14-8395-5ea898056747\" style=\"color:#555555;\">​</span></p><!-- } SE-TEXT --><!-- SE-TEXT { --><p class=\"se-text-paragraph se-text-paragraph-align-\" id=\"SE-5237c967-9253-4144-acaa-aef6d3c8bf27\" style=\"\"><span class=\"se-fs-fs16 se-ff-nanumsquare se-weight-unset\" id=\"SE-b1c549e1-a08a-419c-aa9f-669c1a127878\" style=\"color:#555555;\">온라인 쇼핑몰을 운영하다 보면 한 번쯤 이런 고민을 하게 됩니다.</span></p><!-- } SE-TEXT --><!-- SE-TEXT { --><p class=\"se-text-paragraph se-text-paragraph-align-\" id=\"SE-78462a97-b094-4015-aa09-9e1a22114a13\" style=\"\"><span class=\"se-fs-fs16 se-ff-nanumsquare se-weight-unset\" id=\"SE-128b7426-1247-4797-9353-871f79dc56b5\" style=\"color:#555555;\">​</span></p><!-- } SE-TEXT --><!-- SE-TEXT { --><p class=\"se-text-paragraph se-text-paragraph-align-\" id=\"SE-a2ae2265-c672-4fca-955e-b8405cc3aa47\" style=\"\"><span class=\"se-fs-fs16 se-ff-nanumsquare se-weight-unset\" id=\"SE-276008da-b651-4490-8c73-24096321fc3e\" style=\"color:#555555;\">“상세페이지는 만들었는데 왜 안 팔릴까?”</span></p><!-- } SE-TEXT --><!-- SE-TEXT { --><p class=\"se-text-paragraph se-text-paragraph-align-\" id=\"SE-5e499087-af5e-433c-861a-74645271105c\" style=\"\"><span class=\"se-fs-fs16 se-ff-nanumsquare se-weight-unset\" id=\"SE-bf4b9fd5-473d-404e-a9bf-fe4ff88a0a5d\" style=\"color:#555555;\">“디자인도 예쁜데 전환율이 너무 낮다.”</span></p><!-- } SE-TEXT --><!-- SE-TEXT { --><p class=\"se-text-paragraph se-text-paragraph-align-\" id=\"SE-69650e1f-bb45-422f-a8eb-e1eb76641428\" style=\"\"><span class=\"se-fs-fs16 se-ff-nanumsquare se-weight-unset\" id=\"SE-4e7a974d-8464-4ae1-9ec4-20814131ca5f\" style=\"color:#555555;\">​</span></p><!-- } SE-TEXT --><!-- SE-TEXT { --><p class=\"se-text-paragraph se-text-paragraph-align-\" id=\"SE-c01a9e38-fc20-42c2-a5cc-de514c08a5eb\" style=\"\"><span class=\"se-fs-fs16 se-ff-nanumsquare se-weight-unset\" id=\"SE-f9e6fbe9-7fb5-473a-ae97-1feb52012c0e\" style=\"color:#555555;\">이 문제의 핵심은 </span><span class=\"se-fs-fs19 se-ff-nanumsquare\" id=\"SE-961fb535-c6e5-4309-83ac-01b6db5566d8\" style=\"color:#555555;\"><b>상세페이지 기획</b></span><span class=\"se-fs-fs16 se-ff-nanumsquare se-weight-unset\" id=\"SE-da4e616b-daa9-4816-a19e-1357388e6b3c\" style=\"color:#555555;\">에 있습니다.</span></p><!-- } SE-TEXT -->\n</div>\n</div>\n</div>\n\n</div> <div class=\"se-component se-horizontalLine se-l-default\" id=\"SE-4c7efce4-9b80-4742-ba03-5bc16029402c\">\n<div class=\"se-component-content\">\n<div class=\"se-section se-section-horizontalLine se-l-default se-section-align-\">\n<div class=\"se-module se-module-horizontalLine\">\n<hr class=\"se-hr\"/>\n</div>\n</div>\n</div>\n</div> <div class=\"se-component se-text se-l-default\" id=\"SE-f101ef7c-5103-42f6-a793-44e454149262\">\n<div class=\"se-component-content\">\n<div class=\"se-section se-section-text se-l-default\">\n<div class=\"se-module se-module-text\">\n<!-- SE-TEXT { --><p class=\"se-text-paragraph se-text-paragraph-align-\" id=\"SE-394d4049-da77-4b83-bd6f-f54f4f18a026\" style=\"\"><span class=\"se-fs-fs19 se-ff-nanumsquare se-weight-unset\" id=\"SE-6468cd9b-9718-41f5-9b92-d6a6eaf2a18b\" style=\"color:#0078cb;\">■ 상세페이지 제작에서 가장 중요한 것</span><span class=\"se-fs-fs19 se-ff-nanumsquare se-weight-unset\" id=\"SE-121c42ad-62c6-4703-af97-ece3d87e562b\" style=\"color:#0078cb;\">​</span></p><!-- } SE-TEXT --><!-- SE-TEXT { --><p class=\"se-text-paragraph se-text-paragraph-align-\" id=\"SE-2d4b6311-c304-4459-937b-a1effee94d79\" style=\"\"><span class=\"se-fs-fs16 se-ff-nanumsquare se-weight-unset\" id=\"SE-903f7786-c91e-4e38-8ce8-3e63142204d0\" style=\"color:#555555;\">​</span></p><!-- } SE-TEXT --><!-- SE-TEXT { --><p class=\"se-text-paragraph se-text-paragraph-align-\" id=\"SE-f207a20f-5b22-4a0b-98ed-40b4022446db\" style=\"\"><span class=\"se-fs-fs16 se-ff-nanumsquare se-weight-unset\" id=\"SE-8d6f05c7-3fb8-423b-b9e6-ca3439e518fa\" style=\"color:#555555;background-color:#fff8b2;\">많은 분들이 상세페이지 제작 = 디자인이라고 생각합니다.</span></p><!-- } SE-TEXT --><!-- SE-TEXT { --><p class=\"se-text-paragraph se-text-paragraph-align-\" id=\"SE-42f92f89-2f34-4808-b101-da98c2679e7d\" style=\"\"><span class=\"se-fs-fs16 se-ff-nanumsquare se-weight-unset\" id=\"SE-a7541e5d-0908-4140-b377-edf00379c022\" style=\"color:#555555;background-color:#fff8b2;\">하지만 실제 매출을 만드는 것은 기획 구조입니다. 이점을 (주)파파스컴퍼니은 가장 잘합니다.</span></p><!-- } SE-TEXT --><!-- SE-TEXT { --><p class=\"se-text-paragraph se-text-paragraph-align-\" id=\"SE-54c2f882-b0c3-4c18-93ea-ca855909aed6\" style=\"\"><span class=\"se-fs-fs16 se-ff-nanumsquare se-weight-unset\" id=\"SE-1c2e1715-9dc8-4a11-855c-90e6b1459b30\" style=\"color:#555555;\">​</span></p><!-- } SE-TEXT --><!-- SE-TEXT { --><p class=\"se-text-paragraph se-text-paragraph-align-\" id=\"SE-96a274f1-34c0-46a6-a45d-2ea96db9c26e\" style=\"\"><span class=\"se-fs-fs16 se-ff-nanumsquare se-weight-unset\" id=\"SE-40124829-4ac8-4c98-b4dc-418567d5f87b\" style=\"color:#555555;background-color:#fff8b2;\">상세페이지는 고객이 제품을 보는 페이지가 아니라 구매를 결정하는 페이지입니다.</span></p><!-- } SE-TEXT --><!-- SE-TEXT { --><p class=\"se-text-paragraph se-text-paragraph-align-\" id=\"SE-9e90cedd-ee39-492a-bf66-63ab923324fb\" style=\"\"><span class=\"se-fs-fs16 se-ff-nanumsquare se-weight-unset\" id=\"SE-d68bebd3-76db-4ba3-b0b5-5e9ae07d5b98\" style=\"color:#555555;\">​</span></p><!-- } SE-TEXT --><!-- SE-TEXT { --><p class=\"se-text-paragraph se-text-paragraph-align-\" id=\"SE-468fddc7-52f0-4a62-a8f5-abb80bd7cf62\" style=\"\"><span class=\"se-fs-fs16 se-ff-nanumsquare se-weight-unset\" id=\"SE-6db1c24b-26c7-4596-a5f9-a4c6813d9195\" style=\"color:#555555;\">​</span></p><!-- } SE-TEXT --><!-- SE-TEXT { --><p class=\"se-text-paragraph se-text-paragraph-align-\" id=\"SE-39327b0f-2173-4f0e-9ffc-7576d998ab69\" style=\"\"><span class=\"se-fs-fs16 se-ff-nanumsquare se-weight-unset\" id=\"SE-7d1acb8c-b6d2-48df-9aeb-063fae7621cc\" style=\"color:#555555;\">그래서</span></p><!-- } SE-TEXT --><!-- SE-TEXT { --><p class=\"se-text-paragraph se-text-paragraph-align-\" id=\"SE-fe1de5c6-72a8-42c1-8179-15b324358866\" style=\"\"><span class=\"se-fs-fs16 se-ff-nanumsquare se-weight-unset\" id=\"SE-bc5dc6d1-824e-4735-91a0-865b18299933\" style=\"color:#555555;\">​</span></p><!-- } SE-TEXT --><!-- SE-TEXT { --><p class=\"se-text-paragraph se-text-paragraph-align-\" id=\"SE-c4d8d57f-760a-4be4-8ec7-06e304ec4316\" style=\"\"><span class=\"se-fs-fs16 se-ff-nanumsquare se-weight-unset\" id=\"SE-cd574294-6985-4e1c-adbe-148312746058\" style=\"color:#0078cb;\">□ 어떤 순서로 보여줄지</span></p><!-- } SE-TEXT --><!-- SE-TEXT { --><p class=\"se-text-paragraph se-text-paragraph-align-\" id=\"SE-9c37ea35-10cd-4028-9d28-5f691f6a360b\" style=\"\"><span class=\"se-fs-fs16 se-ff-nanumsquare se-weight-unset\" id=\"SE-b54c9e6a-22da-4d1d-9f05-159710061431\" style=\"color:#0078cb;\">□ 어떤 문장을 먼저 보여줄지</span></p><!-- } SE-TEXT --><!-- SE-TEXT { --><p class=\"se-text-paragraph se-text-paragraph-align-\" id=\"SE-76c4a208-7fba-4fb0-9891-5c73b67521cb\" style=\"\"><span class=\"se-fs-fs16 se-ff-nanumsquare se-weight-unset\" id=\"SE-5ad3daf6-6758-4255-b444-318c7bc72596\" style=\"color:#0078cb;\">□ 어디서 구매 버튼을 누르게 할지</span></p><!-- } SE-TEXT --><!-- SE-TEXT { --><p class=\"se-text-paragraph se-text-paragraph-align-\" id=\"SE-58f55a0a-3610-4470-b364-6a67e538bc1d\" style=\"\"><span class=\"se-fs-fs16 se-ff-nanumsquare se-weight-unset\" id=\"SE-e7757336-dfff-4b96-9c66-66d5611bbd0e\" style=\"color:#555555;\">​</span></p><!-- } SE-TEXT --><!-- SE-TEXT { --><p class=\"se-text-paragraph se-text-paragraph-align-\" id=\"SE-4e22440b-b95a-4bf1-a293-eaec008f7dc6\" style=\"\"><span class=\"se-fs-fs16 se-ff-nanumsquare se-weight-unset\" id=\"SE-50ca7ab4-a92e-4210-8316-99cdc42a2172\" style=\"color:#555555;\">이 모든 것이 상세페이지 기획에서 이미 결정됩니다.</span></p><!-- } SE-TEXT -->\n</div>\n</div>\n</div>\n\n</div> <div class=\"se-component se-horizontalLine se-l-default\" id=\"SE-90fb4244-f179-44de-ab21-5bda5e8e457b\">\n<div class=\"se-component-content\">\n<div class=\"se-section se-section-horizontalLine se-l-default se-section-align-\">\n<div class=\"se-module se-module-horizontalLine\">\n<hr class=\"se-hr\"/>\n</div>\n</div>\n</div>\n</div> <div class=\"se-component se-text se-l-default\" id=\"SE-f7efb9e9-5487-487f-833f-180a6b9cebcd\">\n<div class=\"se-component-content\">\n<div class=\"se-section se-section-text se-l-default\">\n<div class=\"se-module se-module-text\">\n<!-- SE-TEXT { --><p class=\"se-text-paragraph se-text-paragraph-align-\" id=\"SE-d15f07a1-db61-4b32-a69a-fa2322dc2583\" style=\"\"><span class=\"se-fs-fs19 se-ff-nanumsquare se-weight-unset\" id=\"SE-ae017112-d7c3-4f74-83ee-56d9453d109b\" style=\"color:#0078cb;\">■ 왜 상세페이지를 새로 만들어도 안 팔릴까?</span><span class=\"se-fs-fs19 se-ff-nanumsquare se-weight-unset\" id=\"SE-ae693710-b6e4-4faa-9ff1-c71d9bf27bc6\" style=\"color:#0078cb;\">​</span></p><!-- } SE-TEXT -->\n</div>\n</div>\n</div>\n\n</div> <div class=\"se-component se-image se-l-default\" id=\"SE-f12ed6e1-189b-4613-b54b-13ad4a3e34e4\">\n<div class=\"se-component-content se-component-content-normal\">\n<div class=\"se-section se-section-image se-l-default se-section-align-\" style=\"max-width:595px;\">\n<div class=\"se-module se-module-image\" style=\"\">\n<a class=\"se-module-image-link __se_image_link __se_link\" data-linkdata='{\"id\" : \"SE-f12ed6e1-189b-4613-b54b-13ad4a3e34e4\", \"src\" : \"https://mblogthumb-phinf.pstatic.net/MjAyNjAyMTdfMTk5/MDAxNzcxMzA4NjEwMTk5.9-ergiTIAjxHiUnqtFJTMaaJXkaUzNYp8Q4hRAqV-nsg.vnVCeWYofA7Q4n84cye5tRWjKKmO40bQ4fl-6bGvdisg.PNG/%EC%83%B4%ED%91%B8_016.png\", \"originalWidth\" : \"595\", \"originalHeight\" : \"595\", \"linkUse\" : \"false\", \"link\" : \"\", \"fileSize\": \"27661\" }' data-linktype=\"img\" href=\"#\" onclick=\"return false;\" style=\"\">\n<img alt=\"\" class=\"se-image-resource\" src=\"https://mblogthumb-phinf.pstatic.net/MjAyNjAyMTdfMTk5/MDAxNzcxMzA4NjEwMTk5.9-ergiTIAjxHiUnqtFJTMaaJXkaUzNYp8Q4hRAqV-nsg.vnVCeWYofA7Q4n84cye5tRWjKKmO40bQ4fl-6bGvdisg.PNG/%EC%83%B4%ED%91%B8_016.png?type=w966\"/>\n</a>\n</div>\n</div>\n</div>\n\n</div>\n<div class=\"se-component se-text se-l-default\" id=\"SE-0b8e8b11-6322-40ac-a254-acfb70dc46bf\">\n<div class=\"se-component-content\">\n<div class=\"se-section se-section-text se-l-default\">\n<div class=\"se-module se-module-text\">\n<!-- SE-TEXT { --><p class=\"se-text-paragraph se-text-paragraph-align-\" id=\"SE-6cf5c67b-b36d-434c-a2a8-a2e56e1548e3\" style=\"\"><span class=\"se-fs-fs16 se-ff-nanumsquare se-weight-unset\" id=\"SE-86f5ddb2-291a-44f7-9449-2d2ced4ed511\" style=\"color:#555555;\">기존에 제작된 상세페이지를 보면 대부분 이런 구조입니다.</span></p><!-- } SE-TEXT --><!-- SE-TEXT { --><p class=\"se-text-paragraph se-text-paragraph-align-\" id=\"SE-9a8b6ee1-9a41-4fe4-9433-8a9f03dafd51\" style=\"\"><span class=\"se-fs-fs16 se-ff-nanumsquare se-weight-unset\" id=\"SE-f0853c1c-b6fb-4dac-a56e-8a79dd73ef60\" style=\"color:#555555;\">​</span></p><!-- } SE-TEXT --><!-- SE-TEXT { --><p class=\"se-text-paragraph se-text-paragraph-align-\" id=\"SE-1d8b200b-988e-4d61-981d-dc843aa6fdd6\" style=\"\"><span class=\"se-fs-fs16 se-ff-nanumsquare se-weight-unset\" id=\"SE-8cde677e-4004-4136-ac01-ff6a4da457d5\" style=\"color:#ff0010;\">□ 제품 사진</span></p><!-- } SE-TEXT --><!-- SE-TEXT { --><p class=\"se-text-paragraph se-text-paragraph-align-\" id=\"SE-dc5fc303-0ec2-4e4f-9fe0-71d8ea5e3220\" style=\"\"><span class=\"se-fs-fs16 se-ff-nanumsquare se-weight-unset\" id=\"SE-51193169-62f5-49c8-9a19-810d3d7ab3ec\" style=\"color:#ff0010;\">□ 기능 설명</span></p><!-- } SE-TEXT --><!-- SE-TEXT { --><p class=\"se-text-paragraph se-text-paragraph-align-\" id=\"SE-8331640d-4b6a-480c-9de0-210580438078\" style=\"\"><span class=\"se-fs-fs16 se-ff-nanumsquare se-weight-unset\" id=\"SE-cc5a745c-dfbb-487d-bb75-e234ebc6fe68\" style=\"color:#ff0010;\">□ 성분 나열</span></p><!-- } SE-TEXT --><!-- SE-TEXT { --><p class=\"se-text-paragraph se-text-paragraph-align-\" id=\"SE-d16cdf1b-fa5f-4c62-b59b-a9baeb22e0c7\" style=\"\"><span class=\"se-fs-fs16 se-ff-nanumsquare se-weight-unset\" id=\"SE-976145eb-5735-401b-8320-6cdfaf631271\" style=\"color:#ff0010;\">□ 가격</span><span class=\"se-fs-fs16 se-ff-nanumsquare se-weight-unset\" id=\"SE-ca3ef589-8122-43dd-826d-0d0011dda006\" style=\"color:#ff0010;\">​</span></p><!-- } SE-TEXT --><!-- SE-TEXT { --><p class=\"se-text-paragraph se-text-paragraph-align-\" id=\"SE-ccf5b460-cc64-4fe9-9eca-5eaf5842fb20\" style=\"\"><span class=\"se-fs-fs16 se-ff-nanumsquare se-weight-unset\" id=\"SE-278e7037-5ec1-4c17-8cca-923ee4f705bc\" style=\"color:#555555;\">​</span></p><!-- } SE-TEXT --><!-- SE-TEXT { --><p class=\"se-text-paragraph se-text-paragraph-align-\" id=\"SE-0d6be1aa-b7d9-4472-b52e-4002355f3ed6\" style=\"\"><span class=\"se-fs-fs16 se-ff-nanumsquare se-weight-unset\" id=\"SE-73158d89-c1d9-4640-b1a6-a6e191d27cfc\" style=\"color:#555555;\">문제는 고객의 ‘고민’이 빠져 있다는 점입니다.</span></p><!-- } SE-TEXT --><!-- SE-TEXT { --><p class=\"se-text-paragraph se-text-paragraph-align-\" id=\"SE-321f0242-c537-4b94-b7e3-f78e001dd17a\" style=\"\"><span class=\"se-fs-fs16 se-ff-nanumsquare se-weight-unset\" id=\"SE-fe33856c-9d24-45a4-a09c-d348492615a2\" style=\"color:#555555;\">​</span></p><!-- } SE-TEXT --><!-- SE-TEXT { --><p class=\"se-text-paragraph se-text-paragraph-align-\" id=\"SE-8c7f351c-eb32-4509-95a4-113da1510c4a\" style=\"\"><span class=\"se-fs-fs16 se-ff-nanumsquare se-weight-unset\" id=\"SE-71809d93-dcb6-4c16-81f2-ce1c65c28602\" style=\"color:#555555;\">사람들은 샴푸를 사고 싶은 게 아니라 두피 가려움, 떡짐, 탈모 걱정을 해결하고 싶어 합니다.</span></p><!-- } SE-TEXT --><!-- SE-TEXT { --><p class=\"se-text-paragraph se-text-paragraph-align-\" id=\"SE-5f5a4745-85dc-4f4b-bf45-2bf8da82365b\" style=\"\"><span class=\"se-fs-fs16 se-ff-nanumsquare se-weight-unset\" id=\"SE-df3b0601-1f53-4150-bc99-9404bd6fbc7a\" style=\"color:#555555;\">​</span></p><!-- } SE-TEXT --><!-- SE-TEXT { --><p class=\"se-text-paragraph se-text-paragraph-align-\" id=\"SE-2b0d7710-a8a7-4f3d-8158-9dd73d0263ee\" style=\"\"><span class=\"se-fs-fs16 se-ff-nanumsquare se-weight-unset\" id=\"SE-ccb9fc61-3e2f-4d4e-9ac8-5108ce04630e\" style=\"color:#555555;\">상세페이지 기획은 바로 이 부분에서 시작해야 합니다.</span></p><!-- } SE-TEXT -->\n</div>\n</div>\n</div>\n\n</div> <div class=\"se-component se-horizontalLine se-l-line5\" id=\"SE-2a52b6c1-685d-4e8d-8127-143777e4e38f\">\n<div class=\"se-component-content\">\n<div class=\"se-section se-section-horizontalLine se-l-line5 se-section-align-\">\n<div class=\"se-module se-module-horizontalLine\">\n<hr class=\"se-hr\"/>\n</div>\n</div>\n</div>\n</div> <div class=\"se-component se-text se-l-default\" id=\"SE-2e1a83b8-0260-48df-936f-4804bee33fd8\">\n<div class=\"se-component-content\">\n<div class=\"se-section se-section-text se-l-default\">\n<div class=\"se-module se-module-text\">\n<!-- SE-TEXT { --><p class=\"se-text-paragraph se-text-paragraph-align-\" id=\"SE-3caa82ea-2058-42fa-9593-1f0a4d79035c\" style=\"\"><span class=\"se-fs-fs19 se-ff-nanumsquare se-weight-unset\" id=\"SE-f4bdd62c-8836-4e7a-888a-86ce2f73510b\" style=\"color:#0078cb;\">■ </span><span class=\"se-fs-fs19 se-ff-nanumsquare se-weight-unset\" id=\"SE-00b8dc4d-b81b-4438-ad8a-ca2f1942d17e\" style=\"color:#ff0010;\">(주)파파스컴퍼니</span><span class=\"se-fs-fs19 se-ff-nanumsquare se-weight-unset\" id=\"SE-be7aaeb9-9b39-491e-a0eb-d56785540f14\" style=\"color:#0078cb;\">이 만드는 상세페이지는 뭐가 다를까?</span></p><!-- } SE-TEXT --><!-- SE-TEXT { --><p class=\"se-text-paragraph se-text-paragraph-align-\" id=\"SE-f2a87c9e-b4c0-43f4-bff6-97d0406c231e\" style=\"\"><span class=\"se-fs-fs16 se-ff-nanumsquare se-weight-unset\" id=\"SE-b13cd352-2c91-4e34-909d-6dea1d6d260e\" style=\"color:#555555;\">​</span></p><!-- } SE-TEXT --><!-- SE-TEXT { --><p class=\"se-text-paragraph se-text-paragraph-align-\" id=\"SE-eff4d024-48f6-4d4c-be11-465af15d506b\" style=\"\"><span class=\"se-fs-fs16 se-ff-nanumsquare se-weight-unset\" id=\"SE-4a9dfa30-ec26-4772-8ae1-5d95ee9c2226\" style=\"color:#555555;\">저희는 “예쁜 상세페이지”가 아니라 “팔리는 상세페이지”를 만듭니다.</span></p><!-- } SE-TEXT --><!-- SE-TEXT { --><p class=\"se-text-paragraph se-text-paragraph-align-\" id=\"SE-f13370c2-cd4a-4227-a80d-b196ec4293a1\" style=\"\"><span class=\"se-fs-fs16 se-ff-nanumsquare se-weight-unset\" id=\"SE-01d0a9db-8908-424a-a83e-0b698ac3eca1\" style=\"color:#555555;\">​</span></p><!-- } SE-TEXT --><!-- SE-TEXT { --><p class=\"se-text-paragraph se-text-paragraph-align-\" id=\"SE-24120f4e-bbf7-4975-965b-c4795e179e17\" style=\"\"><span class=\"se-fs-fs16 se-ff-nanumsquare se-weight-unset\" id=\"SE-b01e43f0-9533-4472-baa3-deeec7977f56\" style=\"color:#555555;\">제작 과정은 이렇게 진행됩니다.</span></p><!-- } SE-TEXT --><!-- SE-TEXT { --><p class=\"se-text-paragraph se-text-paragraph-align-\" id=\"SE-d0503bae-c486-4bed-98b7-3b66a95296f3\" style=\"\"><span class=\"se-fs-fs16 se-ff-nanumsquare se-weight-unset\" id=\"SE-897a1591-9c49-4c4c-a6ff-0b8475fb6eda\" style=\"color:#555555;\">​</span></p><!-- } SE-TEXT --><!-- SE-TEXT { --><p class=\"se-text-paragraph se-text-paragraph-align-\" id=\"SE-1859e770-edb6-414a-badd-b1d3732fa8ac\" style=\"\"><span class=\"se-fs-fs16 se-ff-nanumsquare se-weight-unset\" id=\"SE-e3100541-766e-4abf-a789-11558cb1b6c2\" style=\"color:#555555;\">1. 타겟 고객 분석</span></p><!-- } SE-TEXT --><!-- SE-TEXT { --><p class=\"se-text-paragraph se-text-paragraph-align-\" id=\"SE-c2de4a5a-e151-447b-bdde-b7384b33f63b\" style=\"\"><span class=\"se-fs-fs16 se-ff-nanumsquare se-weight-unset\" id=\"SE-d3578521-f21a-4760-b7b5-6563d6a3a401\" style=\"color:#555555;\">2. 고객이 겪는 문제 정리</span></p><!-- } SE-TEXT --><!-- SE-TEXT { --><p class=\"se-text-paragraph se-text-paragraph-align-\" id=\"SE-0eabfc9d-5888-4e5f-953d-75fe59f860bc\" style=\"\"><span class=\"se-fs-fs16 se-ff-nanumsquare se-weight-unset\" id=\"SE-3c4115ee-7411-4de6-a597-80e7411658d8\" style=\"color:#555555;\">3. 제품의 핵심 장점 포지셔닝</span></p><!-- } SE-TEXT --><!-- SE-TEXT { --><p class=\"se-text-paragraph se-text-paragraph-align-\" id=\"SE-8946d85b-5e25-48c7-91f6-a09ef0dee20e\" style=\"\"><span class=\"se-fs-fs16 se-ff-nanumsquare se-weight-unset\" id=\"SE-ff17fb80-4c1e-477d-99dc-8e1bf8a32a78\" style=\"color:#555555;\">4. 구매 심리 흐름 설계</span></p><!-- } SE-TEXT --><!-- SE-TEXT { --><p class=\"se-text-paragraph se-text-paragraph-align-\" id=\"SE-100ef8d7-92eb-4160-b04e-90893331590a\" style=\"\"><span class=\"se-fs-fs16 se-ff-nanumsquare se-weight-unset\" id=\"SE-21669c35-ab49-46ac-92a5-c448e5151aee\" style=\"color:#555555;\">5. 그 위에 디자인 적용</span></p><!-- } SE-TEXT --><!-- SE-TEXT { --><p class=\"se-text-paragraph se-text-paragraph-align-\" id=\"SE-90658678-46f1-4745-9e95-8236e85081c2\" style=\"\"><span class=\"se-fs-fs16 se-ff-nanumsquare se-weight-unset\" id=\"SE-6a8ef1ee-058c-4685-a89c-5686833af675\" style=\"color:#555555;\">​</span></p><!-- } SE-TEXT --><!-- SE-TEXT { --><p class=\"se-text-paragraph se-text-paragraph-align-\" id=\"SE-e94e9b2a-dd52-4ec4-bc9c-4fa8f50b4d99\" style=\"\"><span class=\"se-fs-fs16 se-ff-nanumsquare se-weight-unset\" id=\"SE-b975299f-6eb7-411d-91da-596502ce02e4\" style=\"color:#555555;\">이렇게 만들어진 상세페이지는 광고를 붙였을 때 전환율이 눈에 띄게 달라집니다.</span></p><!-- } SE-TEXT -->\n</div>\n</div>\n</div>\n\n</div> <div class=\"se-component se-horizontalLine se-l-default\" id=\"SE-6207ac27-6ba2-4ab5-a024-8ad3164935da\">\n<div class=\"se-component-content\">\n<div class=\"se-section se-section-horizontalLine se-l-default se-section-align-\">\n<div class=\"se-module se-module-horizontalLine\">\n<hr class=\"se-hr\"/>\n</div>\n</div>\n</div>\n</div> <div class=\"se-component se-text se-l-default\" id=\"SE-8484d613-b7df-4ae1-b0f7-f620c5fb71c5\">\n<div class=\"se-component-content\">\n<div class=\"se-section se-section-text se-l-default\">\n<div class=\"se-module se-module-text\">\n<!-- SE-TEXT { --><p class=\"se-text-paragraph se-text-paragraph-align-\" id=\"SE-b15dc17e-7683-4c43-83c2-541cc4b8027e\" style=\"\"><span class=\"se-fs-fs19 se-ff-nanumsquare se-weight-unset\" id=\"SE-3fdcbdbb-6270-4ca0-beb5-b4ca902851fa\" style=\"color:#0078cb;\">■ 이런 분들께 특히 추천합니다.</span></p><!-- } SE-TEXT --><!-- SE-TEXT { --><p class=\"se-text-paragraph se-text-paragraph-align-\" id=\"SE-7da66188-5d3b-474c-a19d-cd747ad1606f\" style=\"\"><span class=\"se-fs-fs16 se-ff-nanumsquare se-weight-unset\" id=\"SE-80728291-1db7-4c08-8221-bfaaa38e901d\" style=\"color:#555555;\">​</span></p><!-- } SE-TEXT --><!-- SE-TEXT { --><p class=\"se-text-paragraph se-text-paragraph-align-\" id=\"SE-4f986822-5d12-4968-ad2b-096a1522b0a0\" style=\"\"><span class=\"se-fs-fs16 se-ff-nanumsquare se-weight-unset\" id=\"SE-b9a5ad05-c652-4b36-8023-260f40a11a99\" style=\"color:#36851e;\">□ 스마트 스토어 매출이 정체된 분</span></p><!-- } SE-TEXT --><!-- SE-TEXT { --><p class=\"se-text-paragraph se-text-paragraph-align-\" id=\"SE-24b66283-2181-4e32-a49f-8930d0af7676\" style=\"\"><span class=\"se-fs-fs16 se-ff-nanumsquare se-weight-unset\" id=\"SE-c0f946c4-ec70-4c46-b1f1-b5a384dade46\" style=\"color:#36851e;\">□ 쿠팡 광고 대비 구매가 적은 분</span></p><!-- } SE-TEXT --><!-- SE-TEXT { --><p class=\"se-text-paragraph se-text-paragraph-align-\" id=\"SE-a0d08957-0d50-477f-8ee2-9b45d966f60b\" style=\"\"><span class=\"se-fs-fs16 se-ff-nanumsquare se-weight-unset\" id=\"SE-98cabb39-7d0a-4ecc-9cf5-7bfde3970bbf\" style=\"color:#36851e;\">□ 제품은 좋은데 반응이 없는 분</span></p><!-- } SE-TEXT --><!-- SE-TEXT { --><p class=\"se-text-paragraph se-text-paragraph-align-\" id=\"SE-56d48f4c-2690-4894-a2dd-8e11527a4d99\" style=\"\"><span class=\"se-fs-fs16 se-ff-nanumsquare se-weight-unset\" id=\"SE-716722af-821c-4860-a483-e3fb96599c8e\" style=\"color:#36851e;\">□ 브랜드 이미지를 만들고 싶은 분</span></p><!-- } SE-TEXT --><!-- SE-TEXT { --><p class=\"se-text-paragraph se-text-paragraph-align-\" id=\"SE-2485dc04-09aa-453f-b204-d2978ff4041a\" style=\"\"><span class=\"se-fs-fs16 se-ff-nanumsquare se-weight-unset\" id=\"SE-be7ef1e2-f645-4dec-be2f-ef46fe03124a\" style=\"color:#555555;\">​</span></p><!-- } SE-TEXT --><!-- SE-TEXT { --><p class=\"se-text-paragraph se-text-paragraph-align-\" id=\"SE-462e1625-0586-44e8-935a-b9c2e5223652\" style=\"\"><span class=\"se-fs-fs16 se-ff-nanumsquare se-weight-unset\" id=\"SE-2a43df2a-bec7-4a40-bada-54ab9afacb04\" style=\"color:#555555;\">상세페이지 하나로 브랜드가 달라질 수 있습니다.</span></p><!-- } SE-TEXT -->\n</div>\n</div>\n</div>\n\n</div> <div class=\"se-component se-horizontalLine se-l-default\" id=\"SE-e845cd8e-a4ea-4369-96c0-fcebc7ec6cc6\">\n<div class=\"se-component-content\">\n<div class=\"se-section se-section-horizontalLine se-l-default se-section-align-\">\n<div class=\"se-module se-module-horizontalLine\">\n<hr class=\"se-hr\"/>\n</div>\n</div>\n</div>\n</div> <div class=\"se-component se-text se-l-default\" id=\"SE-7905aabd-2e91-4a7c-bee5-69ed7dee7a82\">\n<div class=\"se-component-content\">\n<div class=\"se-section se-section-text se-l-default\">\n<div class=\"se-module se-module-text\">\n<!-- SE-TEXT { --><p class=\"se-text-paragraph se-text-paragraph-align-\" id=\"SE-8d05c98a-4191-4b78-932a-a690bcc9f2be\" style=\"\"><span class=\"se-fs-fs19 se-ff-nanumsquare se-weight-unset\" id=\"SE-69d4ab10-6781-451e-8a7d-c76fe58ee2f9\" style=\"color:#0078cb;\">■ 마무리</span></p><!-- } SE-TEXT --><!-- SE-TEXT { --><p class=\"se-text-paragraph se-text-paragraph-align-\" id=\"SE-f8558768-68d5-4ef3-acf8-c459cf07cd8b\" style=\"\"><span class=\"se-fs-fs16 se-ff-nanumsquare se-weight-unset\" id=\"SE-2d4c49d6-a4fb-49ab-9e9b-e33cb5544b46\" style=\"color:#555555;\">​</span></p><!-- } SE-TEXT --><!-- SE-TEXT { --><p class=\"se-text-paragraph se-text-paragraph-align-\" id=\"SE-5d5dca12-7cb2-4d0e-a6e5-cf124d83c5ec\" style=\"\"><span class=\"se-fs-fs16 se-ff-nanumsquare se-weight-unset\" id=\"SE-5374fd3b-a7c3-4f17-ac32-4c59d376bfa2\" style=\"color:#555555;background-color:#ffe3c8;\">지금 사용하는 상세페이지가 “정보만 나열된 페이지”라면 고객은 가격만 비교하고 떠납니다.</span></p><!-- } SE-TEXT --><!-- SE-TEXT { --><p class=\"se-text-paragraph se-text-paragraph-align-\" id=\"SE-7ddca2bd-4102-46ed-ac1e-192f166bc107\" style=\"\"><span class=\"se-fs-fs16 se-ff-nanumsquare se-weight-unset\" id=\"SE-36d01c70-1c89-4b26-9a1d-49d4635b26a3\" style=\"color:#555555;\">​</span></p><!-- } SE-TEXT --><!-- SE-TEXT { --><p class=\"se-text-paragraph se-text-paragraph-align-\" id=\"SE-9a9cefd0-8f3d-4bde-9799-09bb4f4135cc\" style=\"\"><span class=\"se-fs-fs16 se-ff-nanumsquare se-weight-unset\" id=\"SE-49b0359e-37c6-4b5a-b110-f81e79c8b0b0\" style=\"color:#555555;background-color:#ffe3c8;\">하지만 “고객의 문제를 해결해 주는 페이지”가 되면 그때부터 브랜드가 만들어집니다.</span></p><!-- } SE-TEXT --><!-- SE-TEXT { --><p class=\"se-text-paragraph se-text-paragraph-align-\" id=\"SE-dcb8421f-d7a8-440e-9ce2-9b90935bfc23\" style=\"\"><span class=\"se-fs-fs16 se-ff-nanumsquare se-weight-unset\" id=\"SE-ce59e46f-d1a8-4b24-90e3-d98eab247c4d\" style=\"color:#555555;\">​</span></p><!-- } SE-TEXT --><!-- SE-TEXT { --><p class=\"se-text-paragraph se-text-paragraph-align-\" id=\"SE-8154777f-9199-4388-b795-2511b475b5c9\" style=\"\"><span class=\"se-fs-fs16 se-ff-nanumsquare se-weight-unset\" id=\"SE-7fd80f10-d212-40fd-a3ed-c450a879f64b\" style=\"color:#555555;background-color:#ffe3c8;\">상세페이지 제작은 제품을 바꾸지 않고 매출을 바꾸는 가장 빠른 방법입니다.</span></p><!-- } SE-TEXT --><!-- SE-TEXT { --><p class=\"se-text-paragraph se-text-paragraph-align-\" id=\"SE-4ce27c2f-2b21-47a3-aef2-97741551a229\" style=\"\"><span class=\"se-fs-fs16 se-ff-nanumsquare se-weight-unset\" id=\"SE-cee32d73-cd2e-4bda-9e41-cc92f05d3659\" style=\"color:#555555;\">​</span></p><!-- } SE-TEXT -->\n</div>\n</div>\n</div>\n\n</div> <div class=\"se-component se-talktalk se-l-default\" id=\"SE-53910440-e932-4d17-80ef-bd87a85f4fb8\">\n<div class=\"se-component-content\">\n<div class=\"se-section se-section-talktalk se-section-align-center se-l-default\">\n<a class=\"se-module se-module-talktalk\" href=\"https://talk.naver.com/w4tbeb?frm=mblog&amp;ref=https%3A%2F%2Fm.blog.naver.com%2Fcookthedesign%2F224186307141#nafullscreen\" onclick=\"sendClickNlog('pst.talktalk', '');\">\n<span class=\"se-talktalk-banner-text\">\n<span class=\"se-blind\">궁금할 땐 네이버 톡톡하세요!</span>\n</span>\n</a>\n</div>\n</div>\n</div>",
  "media": [
    {
      "url": "https://mblogthumb-phinf.pstatic.net/MjAyNjAyMTdfMTky/MDAxNzcxMzAxNzMxMDQ5.swnqMm5NnH2T29G28XcTH0yyCdareX5IFTXL8sNmI08g.6ER86p2GertmuJgkgxaMht5JE9VlVy4pX7L7HRqtywYg.PNG/Gemini_Generated_Image_7tm0v47tm0v47tm0.png?type=w966",
      "kind": "img"
    },
    {
      "url": "https://mblogthumb-phinf.pstatic.net/MjAyNjAyMTdfNjkg/MDAxNzcxMzA0MjM4NzI0.bL3FYOHwKvxm0LPCsMX9YK64qIsKobPsKkXxGtlTP8Qg.Aeo9oddXqqX52Cr3A-Y5PD8TF-WmsGm11W8WWqBYRGYg.PNG/%EC%83%B4%ED%91%B8_010.png?type=w966",
      "kind": "img"
    },
    {
      "url": "https://mblogthumb-phinf.pstatic.net/MjAyNjAyMThfMjM4/MDAxNzcxMzk2MjQ2NjAw.0YpHtbqmtRD70c2tj2aFchooj8C_dtj3WYpfyqkonKcg._nllVRUfcyu4C9OykM4LRbqI2BSDyaaEIAH6JrofWHcg.PNG/%EC%83%B4%ED%91%B8_014.png?type=w966",
      "kind": "img"
    },
    {
      "url": "https://mblogthumb-phinf.pstatic.net/MjAyNjAyMTdfMTcz/MDAxNzcxMzAzNDg3OTk3.1B4YtRNY2Od7U6EhqDKpP39HXi9G0MHpuM6p8bDY5ekg.6jzxABVUxl5W1ejYRaNqOmjtk3o8Znmk6XTFa_ajYiog.PNG/%EC%83%B4%ED%91%B8_008.png?type=w966",
      "kind": "img"
    },
    {
      "url": "https://mblogthumb-phinf.pstatic.net/MjAyNjAyMTdfMjgg/MDAxNzcxMzAzNDk5MTE5.jMSeno7i21fuTDj3Th4wZpE1_zltMGDbvwYcb44Y0w8g.DCt98cCuIr-YAVN6aO3DMlIeUVczc5byvzT8UWEtz1wg.PNG/%EC%83%B4%ED%91%B8_009.png?type=w966",
      "kind": "img"
    },
    {
      "url": "https://mblogthumb-phinf.pstatic.net/MjAyNjAyMTdfMjYg/MDAxNzcxMzA2NzkyODk3.raTeMYBMg7oGzivpTFaP9C0BiQBmzi5sxnRof--p8VAg.3G4bw_wtFjNaTxMz128OuOAN9XHpwMaTearXyBmXCOUg.PNG/%EC%83%B4%ED%91%B8_013.png?type=w966",
      "kind": "img"
    },
    {
      "url": "https://mblogthumb-phinf.pstatic.net/MjAyNjAyMTdfMTk3/MDAxNzcxMzA2MjAxMTE3.itZYIr60QrJNiC0RWRAZ_ONxPujZFXef7MxL7eGsW3gg.5iUFQ-ZgvcnZNy_2mL-us_9KfsNsnBdxUtVgRgh1ztAg.PNG/%EC%83%B4%ED%91%B8_011.png?type=w966",
      "kind": "img"
    },
    {
      "url": "https://mblogthumb-phinf.pstatic.net/MjAyNjAyMTdfNTMg/MDAxNzcxMzA2NDc4NTU4.5tIIzPlSrPTWUjDSv7fulaoPCqrQGumNgUfmyDB1GPgg.haWwT-xjfrr98OTsM9foEN4Uo-UlnFHmcI2lVeA-hJ4g.PNG/%EC%83%B4%ED%91%B8_012.png?type=w966",
      "kind": "img"
    },
    {
      "url": "https://mblogthumb-phinf.pstatic.net/MjAyNjAyMTdfMTc2/MDAxNzcxMzA4MzIwNjA5.SsH8biqc7v-iORLzKWoRSAuuw2FG-s6xZ08FDMvcKJEg.ZpDp4mFdDHT7XUNuaf0bqvgu1AXYJqpqAgK-7uvGCrQg.PNG/%EC%83%B4%ED%91%B8_015.png?type=w966",
      "kind": "img"
    },
    {
      "url": "https://mblogthumb-phinf.pstatic.net/MjAyNjAyMTdfMTk5/MDAxNzcxMzA4NjEwMTk5.9-ergiTIAjxHiUnqtFJTMaaJXkaUzNYp8Q4hRAqV-nsg.vnVCeWYofA7Q4n84cye5tRWjKKmO40bQ4fl-6bGvdisg.PNG/%EC%83%B4%ED%91%B8_016.png?type=w966",
      "kind": "img"
    }
  ],
  "removed_trailing_images": 2,
  "date": "2026-02-23",
  "image_local": {
    "https://mblogthumb-phinf.pstatic.net/MjAyNjAyMTdfMTky/MDAxNzcxMzAxNzMxMDQ5.swnqMm5NnH2T29G28XcTH0yyCdareX5IFTXL8sNmI08g.6ER86p2GertmuJgkgxaMht5JE9VlVy4pX7L7HRqtywYg.PNG/Gemini_Generated_Image_7tm0v47tm0v47tm0.png?type=w966": "data/images/224186307141/000.png",
    "https://mblogthumb-phinf.pstatic.net/MjAyNjAyMTdfNjkg/MDAxNzcxMzA0MjM4NzI0.bL3FYOHwKvxm0LPCsMX9YK64qIsKobPsKkXxGtlTP8Qg.Aeo9oddXqqX52Cr3A-Y5PD8TF-WmsGm11W8WWqBYRGYg.PNG/%EC%83%B4%ED%91%B8_010.png?type=w966": "data/images/224186307141/001.png",
    "https://mblogthumb-phinf.pstatic.net/MjAyNjAyMThfMjM4/MDAxNzcxMzk2MjQ2NjAw.0YpHtbqmtRD70c2tj2aFchooj8C_dtj3WYpfyqkonKcg._nllVRUfcyu4C9OykM4LRbqI2BSDyaaEIAH6JrofWHcg.PNG/%EC%83%B4%ED%91%B8_014.png?type=w966": "data/images/224186307141/002.png",
    "https://mblogthumb-phinf.pstatic.net/MjAyNjAyMTdfMTcz/MDAxNzcxMzAzNDg3OTk3.1B4YtRNY2Od7U6EhqDKpP39HXi9G0MHpuM6p8bDY5ekg.6jzxABVUxl5W1ejYRaNqOmjtk3o8Znmk6XTFa_ajYiog.PNG/%EC%83%B4%ED%91%B8_008.png?type=w966": "data/images/224186307141/003.png",
    "https://mblogthumb-phinf.pstatic.net/MjAyNjAyMTdfMjgg/MDAxNzcxMzAzNDk5MTE5.jMSeno7i21fuTDj3Th4wZpE1_zltMGDbvwYcb44Y0w8g.DCt98cCuIr-YAVN6aO3DMlIeUVczc5byvzT8UWEtz1wg.PNG/%EC%83%B4%ED%91%B8_009.png?type=w966": "data/images/224186307141/004.png",
    "https://mblogthumb-phinf.pstatic.net/MjAyNjAyMTdfMjYg/MDAxNzcxMzA2NzkyODk3.raTeMYBMg7oGzivpTFaP9C0BiQBmzi5sxnRof--p8VAg.3G4bw_wtFjNaTxMz128OuOAN9XHpwMaTearXyBmXCOUg.PNG/%EC%83%B4%ED%91%B8_013.png?type=w966": "data/images/224186307141/005.png",
    "https://mblogthumb-phinf.pstatic.net/MjAyNjAyMTdfMTk3/MDAxNzcxMzA2MjAxMTE3.itZYIr60QrJNiC0RWRAZ_ONxPujZFXef7MxL7eGsW3gg.5iUFQ-ZgvcnZNy_2mL-us_9KfsNsnBdxUtVgRgh1ztAg.PNG/%EC%83%B4%ED%91%B8_011.png?type=w966": "data/images/224186307141/006.png",
    "https://mblogthumb-phinf.pstatic.net/MjAyNjAyMTdfNTMg/MDAxNzcxMzA2NDc4NTU4.5tIIzPlSrPTWUjDSv7fulaoPCqrQGumNgUfmyDB1GPgg.haWwT-xjfrr98OTsM9foEN4Uo-UlnFHmcI2lVeA-hJ4g.PNG/%EC%83%B4%ED%91%B8_012.png?type=w966": "data/images/224186307141/007.png",
    "https://mblogthumb-phinf.pstatic.net/MjAyNjAyMTdfMTc2/MDAxNzcxMzA4MzIwNjA5.SsH8biqc7v-iORLzKWoRSAuuw2FG-s6xZ08FDMvcKJEg.ZpDp4mFdDHT7XUNuaf0bqvgu1AXYJqpqAgK-7uvGCrQg.PNG/%EC%83%B4%ED%91%B8_015.png?type=w966": "data/images/224186307141/008.png",
    "https://mblogthumb-phinf.pstatic.net/MjAyNjAyMTdfMTk5/MDAxNzcxMzA4NjEwMTk5.9-ergiTIAjxHiUnqtFJTMaaJXkaUzNYp8Q4hRAqV-nsg.vnVCeWYofA7Q4n84cye5tRWjKKmO40bQ4fl-6bGvdisg.PNG/%EC%83%B4%ED%91%B8_016.png?type=w966": "data/images/224186307141/009.png"
  }
}